[15:03:26] [main/DEBUG] [FML/]: Injecting tracing printstreams for STDOUT/STDERR.
[15:03:26] [main/INFO] [FML/]: Forge Mod Loader version 7.99.40.1614 for Minecraft 1.7.10 loading
[15:03:26] [main/INFO] [FML/]: Java is Java HotSpot(TM) 64-Bit Server VM, version 1.8.0_241, running on Windows 10:amd64:10.0, installed at C:\Program Files\Java\jdk1.8.0_241\jre
[15:03:26] [main/DEBUG] [FML/]: Java classpath at launch is C:\Users\sxlga\IdeaProjects\Forge_1.7.10_Template_Schrecktech_Reborn\lib\BrandonsCore-1.0.0.12.jar;C:\Users\sxlga\IdeaProjects\Forge_1.7.10_Template_Schrecktech_Reborn\lib\gregtech-5.09.32pre6.jar;C:\Users\sxlga\IdeaProjects\Forge_1.7.10_Template_Schrecktech_Reborn\lib\GT-PlusPlus-1.7.04.483-dev.jar;C:\Users\sxlga\IdeaProjects\Forge_1.7.10_Template_Schrecktech_Reborn\lib\GTTweaker-1.7.10-1.7.2.jar;C:\Users\sxlga\IdeaProjects\Forge_1.7.10_Template_Schrecktech_Reborn\lib\TGregworks-1.7.10-1.0.18-deobf.jar;C:\Users\sxlga\.gradle\caches\minecraft\net\minecraftforge\forge\1.7.10-10.13.4.1614-1.7.10\start;C:\Users\sxlga\.gradle\caches\modules-2\files-2.1\curse.maven\AIImprovements-1.7.10-0.0.1b19-dev\2252676\2c34459174f9e9b03569a7958cdf6e01a6ba49c4\AIImprovements-1.7.10-0.0.1b19-dev-2252676.jar;C:\Users\sxlga\.gradle\caches\modules-2\files-2.1\applecore\AppleCore\1.7.10-3.1.1\cfa8e0c32e4df66a71f2eb1993608f3025f9f312\AppleCore-1.7.10-3.1.1-deobf.jar;C:\Users\sxlga\.gradle\caches\modules-2\files-2.1\appeng\appliedenergistics2\rv3-beta-6\ca6f08f4f204b20169c05932514a4b5a7425d0a2\appliedenergistics2-rv3-beta-6-dev.jar;C:\Users\sxlga\.gradle\caches\modules-2\files-2.1\curse.maven\ArchitectureCraft-1.7.2-mc1.7.10\2352554\64983af4a9142bd9578fa077069486af641b7a86\ArchitectureCraft-1.7.2-mc1.7.10-2352554.jar;C:\Users\sxlga\.gradle\caches\modules-2\files-2.1\aroma1997core\Aroma1997Core\1.7.10\f86607a5748c70d4614502115070e0e63a266810\Aroma1997Core-1.7.10-1.0.2.16.jar;C:\Users\sxlga\.gradle\caches\modules-2\files-2.1\aromabackup\AromaBackup\1.7.10\6ea72981f34953d39538c206efd34f79ee8860b0\AromaBackup-1.7.10-0.1.0.0.jar;C:\Users\sxlga\.gradle\caches\modules-2\files-2.1\aroma1997s-dimensional-world\Aroma1997s-Dimensional-World\1.7.10\fbc7565a477bb2bb5fda442c47c2667c35f6ad22\Aroma1997s-Dimensional-World-1.7.10-1.1.0.1.jar;C:\Users\sxlga\.gradle\caches\modules-2\files-2.1\com.azanor.baubles\Baubles\1.7.10-1.0.1.10\193ff4efb1d9f19c895dc560e3cd1c141e578f97\Baubles-1.7.10-1.0.1.10-deobf.jar;C:\Users\sxlga\.gradle\caches\modules-2\files-2.1\curse.maven\BetterBuildersWands-0.8.1-1.7.10r92+aec06c3-dev\2356821\acf2f35d55a99048ce562808add5da1954b8d5fe\BetterBuildersWands-0.8.1-1.7.10r92+aec06c3-dev-2356821.jar;C:\Users\sxlga\.gradle\caches\modules-2\files-2.1\curse.maven\biggerpacketsplz-upto1.7.10-1.2\2655844\69de0b989b8e85524e448a0d453ed99b62ddf42f\biggerpacketsplz-upto1.7.10-1.2-2655844.jar;C:\Users\sxlga\.gradle\caches\modules-2\files-2.1\curse.maven\bigtrees-0.2-1.7.10\2273910\3ea1b2bce1951dece100a256aea8b8f13771e016\bigtrees-0.2-1.7.10-2273910.jar;C:\Users\sxlga\.gradle\caches\modules-2\files-2.1\binnie\binnie-mods\1.7.10-2.0.22\770b8e761b2489254ff29bc159acfa543dc75f76\binnie-mods-1.7.10-2.0.22-dev.jar;C:\Users\sxlga\.gradle\caches\modules-2\files-2.1\com.github.glitchfiend.biomesoplenty\BiomesOPlenty\1.7.10-2.1.0.2308\a35a052ed20a93490e169876d6871854a0df58cc\BiomesOPlenty-1.7.10-2.1.0.2308-deobf.jar;C:\Users\sxlga\.gradle\caches\modules-2\files-2.1\curse.maven\Carpenter's Blocks v3.3.8.2 - MC 1.7.10\2719376\a237288349d19459fdd99e8cc1df10ddc3f2ffc0\Carpenter's Blocks v3.3.8.2 - MC 1.7.10-2719376.jar;C:\Users\sxlga\.gradle\caches\modules-2\files-2.1\chisel\Chisel\2.9.5.11\a58ae6a8a00e19d3844253970e2790304b6327de\Chisel-2.9.5.11-deobf.jar;C:\Users\sxlga\.gradle\caches\modules-2\files-2.1\codechicken\CodeChickenCore\1.7.10-1.0.7.47\3f4dff5483cf69915b761ee5a9e9f1865b03b6c4\CodeChickenCore-1.7.10-1.0.7.47-dev.jar;C:\Users\sxlga\.gradle\caches\modules-2\files-2.1\codechicken\CodeChickenLib\1.7.10-1.1.3.140\4a9f6d573d85b066647a93a6018ccb49c8981b20\CodeChickenLib-1.7.10-1.1.3.140-dev.jar;C:\Users\sxlga\.gradle\caches\modules-2\files-2.1\codechicken\ForgeMultipart\1.7.10-1.2.0.347\5ae4eaab5ffee3d61109d9604b4cf05ce97b1570\ForgeMultipart-1.7.10-1.2.0.347-dev.jar;C:\Users\sxlga\.gradle\caches\modules-2\files-2.1\com.builtbroken.codinglib\CodingLib\0.2.8b54\bb4338bf8e2accbf272f7a04fd5638d074e51eab\CodingLib-0.2.8b54.jar;C:\Users\sxlga\.gradle\caches\modules-2\files-2.1\cofh\CoFHCore\1.7.10R3.0.4\9354a90c9dbf527897428c15f19ecab461d8af5d\CoFHCore-1.7.10R3.0.4-dev.jar;C:\Users\sxlga\.gradle\caches\modules-2\files-2.1\cofh\CoFHLib\1.7.10R3.0.3\5603f3dfa2534c3f24a3fa8f0512319eef4c0077\CoFHLib-1.7.10R3.0.3-dev.jar;C:\Users\sxlga\.gradle\caches\modules-2\files-2.1\controlling\Controlling\1.7.10\4f7c4e4807a8f28ce3c31535994e6e0cea0071e\Controlling-1.7.10-1.0.0.jar;C:\Users\sxlga\.gradle\caches\modules-2\files-2.1\curse.maven\cookingbook-mc1.7.10-1.0.140\2299135\15b2a48512d475359451334ff505c912adcef73a\cookingbook-mc1.7.10-1.0.140-2299135.jar;C:\Users\sxlga\.gradle\caches\modules-2\files-2.1\coroutil\coroutil\1.7.10\8f1de498a4bf1b3650bef394209be17648dc1909\coroutil-1.7.10-1.1.6.jar;C:\Users\sxlga\.gradle\caches\modules-2\files-2.1\crafting-tweaks\craftingtweaks\mc1.7.10\9b4ff8b2c59cc78ba45c1d648cbd23ad01c53d45\craftingtweaks-mc1.7.10-1.0.88.jar;C:\Users\sxlga\.gradle\caches\modules-2\files-2.1\curse.maven\CraftTweaker-1.7.10-3.1.0-legacy\2838720\ecd735d334578d127b75fc4a680a2a8043e0f5d5\CraftTweaker-1.7.10-3.1.0-legacy-2838720.jar;C:\Users\sxlga\.gradle\caches\modules-2\files-2.1\curse.maven\Draconic-Evolution-1.7.10-1.0.2h-deobf\2313452\db35d9aee34be1551fda2deb37180ab7ea5bb865\Draconic-Evolution-1.7.10-1.0.2h-deobf-2313452.jar;C:\Users\sxlga\.gradle\caches\modules-2\files-2.1\curse.maven\EnchantingPlus-1.7.10-3.0.2-d\2218324\2b84db09fc8875c2726a4b93d3ed37bc6ba16340\EnchantingPlus-1.7.10-3.0.2-d-2218324.jar;C:\Users\sxlga\.gradle\caches\modules-2\files-2.1\curse.maven\EnhancedPortals-1.7.10-universal-3.0.12\2242378\fd5864a46f77b51cb92428e882e68d921aa66a6d\EnhancedPortals-1.7.10-universal-3.0.12-2242378.jar;C:\Users\sxlga\.gradle\caches\modules-2\files-2.1\curse.maven\externaltweaker-1.7.10-FINAL-0.3\2452853\3ede7025787545fd84a82bfff579ec4baea2894b\externaltweaker-1.7.10-FINAL-0.3-2452853.jar;C:\Users\sxlga\.gradle\caches\modules-2\files-2.1\curse.maven\extrabiomesxl.1.7.10-3.16.4\2273301\ae12fc1826b53a53f4c5d231de2b4c8b1dea18cb\extrabiomesxl.1.7.10-3.16.4-2273301.jar;C:\Users\sxlga\.gradle\caches\modules-2\files-2.1\extracells\ExtraCells\1.7.10-2.3.14b200\c4e1fe3c4d7fb41f5b22bb49b7fe7d06f471ac77\ExtraCells-1.7.10-2.3.14b200-deobf.jar;C:\Users\sxlga\.gradle\caches\modules-2\files-2.1\curse.maven\extrautilities-1.2.12-deobf\2264384\6bb0ce28f686ee151f5674bfb9df59777c9352e4\extrautilities-1.2.12-deobf-2264384.jar;C:\Users\sxlga\.gradle\caches\modules-2\files-2.1\farseek\Farseek\1.7.10\615e8b0a93f083a50ac1f6d703d4ddf8bc269446\Farseek-1.7.10-2.0.1.jar;C:\Users\sxlga\.gradle\caches\modules-2\files-2.1\net.sengir.forestry\forestry_1.7.10\4.2.16.64\92b0e3abf579545f252a98a0e523ed4234f13b4a\forestry_1.7.10-4.2.16.64-dev.jar;C:\Users\sxlga\.gradle\caches\modules-2\files-2.1\com.amadornes.framez\Framez\1.7.10-0.2-33\326a81f5a48f8b361188998494c77060dac7ef00\Framez-1.7.10-0.2-33-deobf.jar;C:\Users\sxlga\.gradle\caches\modules-2\files-2.1\se.gory_moon\GlobalGameRules\1.7.10-1.0\2ef433ce61e7440d087dd53fb2bf3e8a18b77c45\GlobalGameRules-1.7.10-1.0.jar;C:\Users\sxlga\.gradle\caches\modules-2\files-2.1\hardcore-darkness\HardcoreDarkness\MC1.7.10\9aaabc413f0f0b9915d6e38a7579b87eab227db3\HardcoreDarkness-MC1.7.10-1.7.jar;C:\Users\sxlga\.gradle\caches\modules-2\files-2.1\curse.maven\HelpFixer-1.0.7\2223813\9e2806c77f9bdbc01510b2794e2b1af5a604f4f0\HelpFixer-1.0.7-2223813.jar;C:\Users\sxlga\.gradle\caches\modules-2\files-2.1\nuclear-control-2\IC2NuclearControl\2.4.3a\ad5156b37828ffa0b8db9363420c69b061d9e7e6\IC2NuclearControl-2.4.3a-dev.jar;C:\Users\sxlga\.gradle\caches\modules-2\files-2.1\ichunutil\iChunUtil\4.2.3\4e3eb786d262e58ae6f8d9921fe50aff7ad4f7a3\iChunUtil-4.2.3-deobf.jar;C:\Users\sxlga\.gradle\caches\modules-2\files-2.1\net.industrial-craft\industrialcraft-2\2.2.828-experimental\bb8a1d7fd468c9798fad96d5b32bb2ce7bd5c2a1\industrialcraft-2-2.2.828-experimental-dev.jar;C:\Users\sxlga\.gradle\caches\modules-2\files-2.1\atomicstrykers-infernal-mobs\InfernalMobs\1.7.10\fc41e4a6f90a15044ca6bd0e40f22be8dc8fe3c\InfernalMobs-1.7.10.jar;C:\Users\sxlga\.gradle\caches\modules-2\files-2.1\infini-tic\Infini-TiC\1.7.10\8aec67f15b5efa28d9d421913be4bee33b05fe28\Infini-TiC-1.7.10-0.1.5.DEV.324b697.jar;C:\Users\sxlga\.gradle\caches\modules-2\files-2.1\curse.maven\INpureCore-[1.7.10]1.0.0B9-62\2238507\83e774abd91fa98e4ee809d724085116d0e155b6\INpureCore-[1.7.10]1.0.0B9-62-2238507.jar;C:\Users\sxlga\.gradle\caches\modules-2\files-2.1\curse.maven\2210792\3643e09b93e66c5690de7b9c3daa62da7789e7f5\-2210792.jar;C:\Users\sxlga\.gradle\caches\modules-2\files-2.1\iron-chests\ironchest-1.7.10\6.0.62.742\2888052ca2727a875ac13fa266e74b53e90cfab4\ironchest-1.7.10-6.0.62.742-universal.jar;C:\Users\sxlga\.gradle\caches\modules-2\files-2.1\mcp.mobius.jabba\Jabba\1.2.2_1.7.10\4fe900b7e95afb87b06744212a3467e57b0aa606\Jabba-1.2.2_1.7.10-dev.jar;C:\Users\sxlga\.gradle\caches\modules-2\files-2.1\journeymap\journeymap-1.7.10\5.1.4p2\dd3ef105a039afaae08dc9ac46c2368d8e462951\journeymap-1.7.10-5.1.4p2-unlimited.jar;C:\Users\sxlga\.gradle\caches\modules-2\files-2.1\magic-bees\magicbees\1.7.10\7da02149dcdcfb8d6e4e52fcaea1c592c138d54b\magicbees-1.7.10-2.4.4.jar;C:\Users\sxlga\.gradle\caches\modules-2\files-2.1\curse.maven\malisiscore-1.7.10-0.14.3-dev\2283268\9d969b691db830bf5b1149048453fa7e251c3afa\malisiscore-1.7.10-0.14.3-dev-2283268.jar;C:\Users\sxlga\.gradle\caches\modules-2\files-2.1\curse.maven\malisisdoors-1.7.10-1.13.2-dev\2284381\c63d4ffed4c91d3bd1b9e2990fe4eb0629fc7efb\malisisdoors-1.7.10-1.13.2-dev-2284381.jar;C:\Users\sxlga\.gradle\caches\modules-2\files-2.1\mantle\Mantle\1.7.10\56552968dc8df9a3ad0f909024d086f3748844dc\Mantle-1.7.10-0.3.2b.jar;C:\Users\sxlga\.gradle\caches\modules-2\files-2.1\minetweaker-recipemaker\MineTweakerRecipeMaker\1.7.10\9bc031c0b0db065651744f23df48f766743892ba\MineTweakerRecipeMaker-1.7.10-1.1.1.jar;C:\Users\sxlga\.gradle\caches\modules-2\files-2.1\curse.maven\MobAmputation-4.0.1\2239204\e48a3cce7962cc801bf62b89debf8c6efe85766b\MobAmputation-4.0.1-2239204.jar;C:\Users\sxlga\.gradle\caches\modules-2\files-2.1\curse.maven\MobDismemberment-4.0.0\2232121\36d8b5d287e038be0e1fe7888d6096efe14b5dab\MobDismemberment-4.0.0-2232121.jar;C:\Users\sxlga\.gradle\caches\modules-2\files-2.1\curse.maven\Modpack Configuration Checker-1.7.10-v1.5.3\2713414\53583f6e09c30d81cce71083c09f27f86676da8f\Modpack Configuration Checker-1.7.10-v1.5.3-2713414.jar;C:\Users\sxlga\.gradle\caches\modules-2\files-2.1\curse.maven\MoreChisels-1.7.10-1.0.28-deobf\2263982\92b8a3ded5471ba6d18c2f6b1dda56c1b3db0cd6\MoreChisels-1.7.10-1.0.28-deobf-2263982.jar;C:\Users\sxlga\.gradle\caches\modules-2\files-2.1\morpheus\Morpheus\1.7.10\b6f94b849d8a4a106f4aca32a9d1ede9b55cc5c5\Morpheus-1.7.10-1.6.21.jar;C:\Users\sxlga\.gradle\caches\modules-2\files-2.1\mouse-tweaks\MouseTweaks\2.4.4\1fef53ebcd48f003fa0799de51e86ad113e3af7c\MouseTweaks-2.4.4-mc1.7.10.jar;C:\Users\sxlga\.gradle\caches\modules-2\files-2.1\natura\natura\1.7.10\95ca39e8ffb89e84192a7d9a2f649e2896a9b561\natura-1.7.10-2.2.1a2.jar;C:\Users\sxlga\.gradle\caches\modules-2\files-2.1\natures-compass\NaturesCompass\1.7.10\470b45aa127e3ff619d4ae2d764613f8d7493c8a\NaturesCompass-1.7.10-1.3.1.jar;C:\Users\sxlga\.gradle\caches\modules-2\files-2.1\curse.maven\Neat 1.0-1\2268525\efb6219d83e6ec1fdb5a9625acc79b1fad723248\Neat 1.0-1-2268525.jar;C:\Users\sxlga\.gradle\caches\modules-2\files-2.1\netherportalfix\netherportalfix\mc1.7.10\c812e8edc89718fd1ecc5d6bdb0855a0ac4f62f1\netherportalfix-mc1.7.10-1.1.0.jar;C:\Users\sxlga\.gradle\caches\modules-2\files-2.1\curse.maven\NoMoreRecipeConflict-0.3(1.7.10)\2267374\fb2936b66646761230d447c7529d8b4429736b9e\NoMoreRecipeConflict-0.3(1.7.10)-2267374.jar;C:\Users\sxlga\.gradle\caches\modules-2\files-2.1\curse.maven\NotEnoughIDs-1.4.2-deobf\2275081\922950c29b69e56b0ad3a84cfb4335e14bf348c6\NotEnoughIDs-1.4.2-deobf-2275081.jar;C:\Users\sxlga\.gradle\caches\modules-2\files-2.1\curse.maven\NotEnoughItems-1.7.10-2.0.1-GTNH-universal\2906319\e222ef0b95bab25b0c7f8fdee5c0e46cbba2ffbc\NotEnoughItems-1.7.10-2.0.1-GTNH-universal-2906319.jar;C:\Users\sxlga\.gradle\caches\modules-2\files-2.1\curse.maven\NotEnoughKeys-1.7.10.3.0.0b45.dev-universal\2276280\4db84b196e1e2a403edbd9d9ee584552da2f7f1f\NotEnoughKeys-1.7.10.3.0.0b45.dev-universal-2276280.jar;C:\Users\sxlga\.gradle\caches\modules-2\files-2.1\curse.maven\NotEnoughResources-1.7.10-0.1.0-128\2323485\8da5097b7b13050f246ced9573eee23d5e069c2a\NotEnoughResources-1.7.10-0.1.0-128-2323485.jar;C:\Users\sxlga\.gradle\caches\modules-2\files-2.1\openblocks\OpenBlocks\1.7.10-1.6-1.7.10\cbc6ac38b8614d267e915fb096cd39311c39758c\OpenBlocks-1.7.10-1.6-1.7.10-deobf.jar;C:\Users\sxlga\.gradle\caches\modules-2\files-2.1\li.cil.oc\OpenComputers\MC1.7.10-1.7.2.1204\23ea8e10318530e74a6a845d8743a6ad0238c00\OpenComputers-MC1.7.10-1.7.2.1204-dev.jar;C:\Users\sxlga\.gradle\caches\modules-2\files-2.1\openmods\OpenModsLib\1.7.10-0.10\266d0d1772b6e53a180d8d80931e5a2e3c16142b\OpenModsLib-1.7.10-0.10-deobf.jar;C:\Users\sxlga\.gradle\caches\modules-2\files-2.1\curse.maven\OpenModularTurrets-1.7.10-2.2.11-245\2549788\7dae300d154be8df1503cfdd1d4a498ce99c4744\OpenModularTurrets-1.7.10-2.2.11-245-2549788.jar;C:\Users\sxlga\.gradle\caches\modules-2\files-2.1\p455w0rds-library\p455w0rdslib\1.7.10\ad6f3ad049611d1a238acb965e0b68d61998d81e\p455w0rdslib-1.7.10-1.0.4.jar;C:\Users\sxlga\.gradle\caches\modules-2\files-2.1\curse.maven\Pam's Get all the Seeds 1.7.10a\2245851\5fad0ef34590bdf91f8d0bfb3cb33f2d020508fe\Pam's Get all the Seeds 1.7.10a-2245851.jar;C:\Users\sxlga\.gradle\caches\modules-2\files-2.1\curse.maven\Pam's Harvest the Nether 1.7.10a\2241397\d32d802bbaa55c11e1f06e0ea5f1994a136c9b5d\Pam's Harvest the Nether 1.7.10a-2241397.jar;C:\Users\sxlga\.gradle\caches\modules-2\files-2.1\curse.maven\Pam's HarvestCraft 1.7.10Lb\2270206\5f85c3fcbf8586a438030c216c4fe37c7a6402c0\Pam's HarvestCraft 1.7.10Lb-2270206.jar;C:\Users\sxlga\.gradle\caches\modules-2\files-2.1\practical-logistics\Practical-Logistics-1.7.10\0.2.4\756902085f6df55983e7c9902d332a5d00523ac3\Practical-Logistics-1.7.10-0.2.4-dev.jar;C:\Users\sxlga\.gradle\caches\modules-2\files-2.1\mrtjp\ProjectRed\1.7.10-4.7.0pre9.52\64dc5f9d945e833ce314d2ec96ffa96c0777c14a\ProjectRed-1.7.10-4.7.0pre9.52-dev.jar;C:\Users\sxlga\.gradle\caches\modules-2\files-2.1\mods.railcraft\Railcraft_1.7.10\9.12.3.0\6064f4ee6c4057949ec80e90bb5cb9d4bf28dc11\Railcraft_1.7.10-9.12.3.0-dev.jar;C:\Users\sxlga\.gradle\caches\modules-2\files-2.1\curse.maven\ReAuth-3.5.0\2433392\1ffe69eb1ac0b0499f3bdaf8990c85e20e69327f\ReAuth-3.5.0-2433392.jar;C:\Users\sxlga\.gradle\caches\modules-2\files-2.1\roguelike-dungeons\roguelike\1.7.10\ad43bc7492081f8c2cc9003754defa47aa798971\roguelike-1.7.10-1.5.0b.jar;C:\Users\sxlga\.gradle\caches\modules-2\files-2.1\realistic-terrain-generation\RTG\1.7.10\7d542c0e06b4a543468f033e365fee01d8bdd91b\RTG-1.7.10-1.1.1.7.jar;C:\Users\sxlga\.gradle\caches\modules-2\files-2.1\sonar-core\SonarCore-1.7.10\1.1.3\69908ebcda3941467ea1931c8a53978bbecfcef7\SonarCore-1.7.10-1.1.3-dev.jar;C:\Users\sxlga\.gradle\caches\modules-2\files-2.1\streams\Streams\1.7.10\9ead1486d85c1bf120ddd7fc284ff2091b3d9f61\Streams-1.7.10-0.3.4.jar;C:\Users\sxlga\.gradle\caches\modules-2\files-2.1\tinkers-construct\TConstruct\1.7.10\35e7ee78cd1f8b185373a6b91de252fa14755f3f\TConstruct-1.7.10-1.8.8.build991.jar;C:\Users\sxlga\.gradle\caches\modules-2\files-2.1\tic-tooltips\TiCTooltips\mc1.7.10\5a3b97262bd10cf639974251bfda1a35f4b61127\TiCTooltips-mc1.7.10-1.2.5.jar;C:\Users\sxlga\.gradle\caches\modules-2\files-2.1\mcp.mobius.waila\Waila\1.5.10_1.7.10\15d268565941880488ac81ac13ad185123bbbfbd\Waila-1.5.10_1.7.10-dev.jar;C:\Users\sxlga\.gradle\caches\modules-2\files-2.1\waila-features\WAILA-features\1.7.10\b94af72d52aa1534b44d295197db462d9d8d8440\WAILA-features-1.7.10-0.1.0.jar;C:\Users\sxlga\.gradle\caches\modules-2\files-2.1\curse.maven\WarpDrive-1.7.10-1.4.2\2578306\fbcf32d155a90a4d79c6185094c0790631bef22d\WarpDrive-1.7.10-1.4.2-2578306.jar;C:\Users\sxlga\.gradle\caches\modules-2\files-2.1\curse.maven\Wawla-1.0.5.120\2298772\85fb074320b2cacb1dec790ab894f7d57a67b2ef\Wawla-1.0.5.120-2298772.jar;C:\Users\sxlga\.gradle\caches\modules-2\files-2.1\curse.maven\WirelessCraftingTerminal-1.7.10-rv3-1.8.7.9b-deobf\2460356\dd1702353ba1b39a37684e589ed68cc6115a98d5\WirelessCraftingTerminal-1.7.10-rv3-1.8.7.9b-deobf-2460356.jar;C:\Users\sxlga\.gradle\caches\modules-2\files-2.1\zombie-awareness\zombieawareness\1.7.10\ee0fdc9ac7ecfc85088dc97bb74368431623419d\zombieawareness-1.7.10-1.10.jar;C:\Users\sxlga\.gradle\caches\modules-2\files-2.1\ztones\Ztones\1.7.10\33a1fbcc7e153037e5092f3b59a61365c6500e96\Ztones-1.7.10-2.2.1.jar;C:\Users\sxlga\.gradle\caches\modules-2\files-2.1\mrtjp\MrTJPCore\1.7.10-1.0.8.16\c9a699f367e5cb80ede60150292b87581c3504e5\MrTJPCore-1.7.10-1.0.8.16-dev.jar;C:\Users\sxlga\.gradle\caches\modules-2\files-2.1\yuutolib\YuutoLib-1.7.10\1.0.3\d1c00243d345a9303f85cf467b1c46b4c378ee3c\YuutoLib-1.7.10-1.0.3-dev.jar;C:\Users\sxlga\.gradle\caches\modules-2\files-2.1\curse.maven\[1.7.10]bspkrsCore-universal-6.16\2227503\b591d7b526794c0b9d22d10e0a0b46636c10fce3\[1.7.10]bspkrsCore-universal-6.16-2227503.jar;C:\Users\sxlga\.gradle\caches\minecraft\net\minecraftforge\forge\1.7.10-10.13.4.1614-1.7.10\stable\12\forgeSrc-1.7.10-10.13.4.1614-1.7.10.jar;C:\Users\sxlga\.gradle\caches\modules-2\files-2.1\net.minecraft\launchwrapper\1.12\111e7bea9c968cdb3d06ef4632bf7ff0824d0f36\launchwrapper-1.12.jar;C:\Users\sxlga\.gradle\caches\modules-2\files-2.1\com.google.code.findbugs\jsr305\1.3.9\40719ea6961c0cb6afaeb6a921eaa1f6afd4cfdf\jsr305-1.3.9.jar;C:\Users\sxlga\.gradle\caches\modules-2\files-2.1\org.ow2.asm\asm-debug-all\5.0.3\f9e364ae2a66ce2a543012a4668856e84e5dab74\asm-debug-all-5.0.3.jar;C:\Users\sxlga\.gradle\caches\modules-2\files-2.1\com.typesafe.akka\akka-actor_2.11\2.3.3\ed62e9fc709ca0f2ff1a3220daa8b70a2870078e\akka-actor_2.11-2.3.3.jar;C:\Users\sxlga\.gradle\caches\modules-2\files-2.1\com.typesafe\config\1.2.1\f771f71fdae3df231bcd54d5ca2d57f0bf93f467\config-1.2.1.jar;C:\Users\sxlga\.gradle\caches\modules-2\files-2.1\org.scala-lang\scala-actors-migration_2.11\1.1.0\dfa8bc42b181d5b9f1a5dd147f8ae308b893eb6f\scala-actors-migration_2.11-1.1.0.jar;C:\Users\sxlga\.gradle\caches\modules-2\files-2.1\org.scala-lang\scala-compiler\2.11.1\56ea2e6c025e0821f28d73ca271218b8dd04926a\scala-compiler-2.11.1.jar;C:\Users\sxlga\.gradle\caches\modules-2\files-2.1\org.scala-lang.plugins\scala-continuations-library_2.11\1.0.2\e517c53a7e9acd6b1668c5a35eccbaa3bab9aac\scala-continuations-library_2.11-1.0.2.jar;C:\Users\sxlga\.gradle\caches\modules-2\files-2.1\org.scala-lang.plugins\scala-continuations-plugin_2.11.1\1.0.2\f361a3283452c57fa30c1ee69448995de23c60f7\scala-continuations-plugin_2.11.1-1.0.2.jar;C:\Users\sxlga\.gradle\caches\modules-2\files-2.1\org.scala-lang\scala-library\2.11.1\e11da23da3eabab9f4777b9220e60d44c1aab6a\scala-library-2.11.1.jar;C:\Users\sxlga\.gradle\caches\modules-2\files-2.1\org.scala-lang\scala-parser-combinators_2.11\1.0.1\f05d7345bf5a58924f2837c6c1f4d73a938e1ff0\scala-parser-combinators_2.11-1.0.1.jar;C:\Users\sxlga\.gradle\caches\modules-2\files-2.1\org.scala-lang\scala-reflect\2.11.1\6580347e61cc7f8e802941e7fde40fa83b8badeb\scala-reflect-2.11.1.jar;C:\Users\sxlga\.gradle\caches\modules-2\files-2.1\org.scala-lang\scala-swing_2.11\1.0.1\b1cdd92bd47b1e1837139c1c53020e86bb9112ae\scala-swing_2.11-1.0.1.jar;C:\Users\sxlga\.gradle\caches\modules-2\files-2.1\org.scala-lang\scala-xml_2.11\1.0.2\7a80ec00aec122fba7cd4e0d4cdd87ff7e4cb6d0\scala-xml_2.11-1.0.2.jar;C:\Users\sxlga\.gradle\caches\modules-2\files-2.1\net.sf.jopt-simple\jopt-simple\4.5\6065cc95c661255349c1d0756657be17c29a4fd3\jopt-simple-4.5.jar;C:\Users\sxlga\.gradle\caches\modules-2\files-2.1\lzma\lzma\0.0.1\521616dc7487b42bef0e803bd2fa3faf668101d7\lzma-0.0.1.jar;C:\Users\sxlga\.gradle\caches\modules-2\files-2.1\com.mojang\realms\1.3.5\807ae355ee63583becd7ea60e76aab1532bb42e\realms-1.3.5.jar;C:\Users\sxlga\.gradle\caches\modules-2\files-2.1\org.apache.commons\commons-compress\1.8.1\a698750c16740fd5b3871425f4cb3bbaa87f529d\commons-compress-1.8.1.jar;C:\Users\sxlga\.gradle\caches\modules-2\files-2.1\org.apache.httpcomponents\httpclient\4.3.3\18f4247ff4572a074444572cee34647c43e7c9c7\httpclient-4.3.3.jar;C:\Users\sxlga\.gradle\caches\modules-2\files-2.1\commons-logging\commons-logging\1.1.3\f6f66e966c70a83ffbdb6f17a0919eaf7c8aca7f\commons-logging-1.1.3.jar;C:\Users\sxlga\.gradle\caches\modules-2\files-2.1\org.apache.httpcomponents\httpcore\4.3.2\31fbbff1ddbf98f3aa7377c94d33b0447c646b6e\httpcore-4.3.2.jar;C:\Users\sxlga\.gradle\caches\modules-2\files-2.1\java3d\vecmath\1.3.1\a0ae4f51da409fa0c20fa0ca59e6bbc9413ae71d\vecmath-1.3.1.jar;C:\Users\sxlga\.gradle\caches\modules-2\files-2.1\net.sf.trove4j\trove4j\3.0.3\42ccaf4761f0dfdfa805c9e340d99a755907e2dd\trove4j-3.0.3.jar;C:\Users\sxlga\.gradle\caches\modules-2\files-2.1\com.ibm.icu\icu4j-core-mojang\51.2\63d216a9311cca6be337c1e458e587f99d382b84\icu4j-core-mojang-51.2.jar;C:\Users\sxlga\.gradle\caches\modules-2\files-2.1\com.paulscode\codecjorbis\20101023\c73b5636faf089d9f00e8732a829577de25237ee\codecjorbis-20101023.jar;C:\Users\sxlga\.gradle\caches\modules-2\files-2.1\com.paulscode\codecwav\20101023\12f031cfe88fef5c1dd36c563c0a3a69bd7261da\codecwav-20101023.jar;C:\Users\sxlga\.gradle\caches\modules-2\files-2.1\com.paulscode\libraryjavasound\20101123\5c5e304366f75f9eaa2e8cca546a1fb6109348b3\libraryjavasound-20101123.jar;C:\Users\sxlga\.gradle\caches\modules-2\files-2.1\com.paulscode\librarylwjglopenal\20100824\73e80d0794c39665aec3f62eee88ca91676674ef\librarylwjglopenal-20100824.jar;C:\Users\sxlga\.gradle\caches\modules-2\files-2.1\com.paulscode\soundsystem\20120107\419c05fe9be71f792b2d76cfc9b67f1ed0fec7f6\soundsystem-20120107.jar;C:\Users\sxlga\.gradle\caches\modules-2\files-2.1\io.netty\netty-all\4.0.10.Final\9e50bd52ffe257a0e2cd8d971688d6ce7d174325\netty-all-4.0.10.Final.jar;C:\Users\sxlga\.gradle\caches\modules-2\files-2.1\com.google.guava\guava\17.0\9c6ef172e8de35fd8d4d8783e4821e57cdef7445\guava-17.0.jar;C:\Users\sxlga\.gradle\caches\modules-2\files-2.1\org.apache.commons\commons-lang3\3.3.2\90a3822c38ec8c996e84c16a3477ef632cbc87a3\commons-lang3-3.3.2.jar;C:\Users\sxlga\.gradle\caches\modules-2\files-2.1\commons-io\commons-io\2.4\b1b6ea3b7e4aa4f492509a4952029cd8e48019ad\commons-io-2.4.jar;C:\Users\sxlga\.gradle\caches\modules-2\files-2.1\commons-codec\commons-codec\1.9\9ce04e34240f674bc72680f8b843b1457383161a\commons-codec-1.9.jar;C:\Users\sxlga\.gradle\caches\modules-2\files-2.1\net.java.jinput\jinput\2.0.5\39c7796b469a600f72380316f6b1f11db6c2c7c4\jinput-2.0.5.jar;C:\Users\sxlga\.gradle\caches\modules-2\files-2.1\net.java.jutils\jutils\1.0.0\e12fe1fda814bd348c1579329c86943d2cd3c6a6\jutils-1.0.0.jar;C:\Users\sxlga\.gradle\caches\modules-2\files-2.1\com.google.code.gson\gson\2.2.4\a60a5e993c98c864010053cb901b7eab25306568\gson-2.2.4.jar;C:\Users\sxlga\.gradle\caches\modules-2\files-2.1\com.mojang\authlib\1.5.16\ef1582b11fd0943d069cdcb72e99008ac209a283\authlib-1.5.16.jar;C:\Users\sxlga\.gradle\caches\modules-2\files-2.1\org.apache.logging.log4j\log4j-api\2.0-beta9\1dd66e68cccd907880229f9e2de1314bd13ff785\log4j-api-2.0-beta9.jar;C:\Users\sxlga\.gradle\caches\modules-2\files-2.1\org.apache.logging.log4j\log4j-core\2.0-beta9\678861ba1b2e1fccb594bb0ca03114bb05da9695\log4j-core-2.0-beta9.jar;C:\Users\sxlga\.gradle\caches\modules-2\files-2.1\org.lwjgl.lwjgl\lwjgl\2.9.1\f58c5aabcef0e41718a564be9f8e412fff8db847\lwjgl-2.9.1.jar;C:\Users\sxlga\.gradle\caches\modules-2\files-2.1\org.lwjgl.lwjgl\lwjgl_util\2.9.1\290d7ba8a1bd9566f5ddf16ad06f09af5ec9b20e\lwjgl_util-2.9.1.jar;C:\Users\sxlga\.gradle\caches\modules-2\files-2.1\tv.twitch\twitch\5.16\1f55f009c61637c10c0acfb8b5ffc600f30044b4\twitch-5.16.jar;C:\Users\sxlga\.gradle\caches\modules-2\files-2.1\org.scala-lang\scala-actors\2.11.0\8ccfb6541de179bb1c4d45cf414acee069b7f78b\scala-actors-2.11.0.jar;C:\Users\sxlga\.gradle\caches\modules-2\files-2.1\org.scala-lang.modules\scala-xml_2.11\1.0.2\820fbca7e524b530fdadc594c39d49a21ea0337e\scala-xml_2.11-1.0.2.jar;C:\Users\sxlga\.gradle\caches\modules-2\files-2.1\org.scala-lang.modules\scala-parser-combinators_2.11\1.0.1\f05d7345bf5a58924f2837c6c1f4d73a938e1ff0\scala-parser-combinators_2.11-1.0.1.jar;C:\Users\sxlga\.gradle\caches\modules-2\files-2.1\net.java.jinput\jinput-platform\2.0.5\7ff832a6eb9ab6a767f1ade2b548092d0fa64795\jinput-platform-2.0.5-natives-linux.jar;C:\Users\sxlga\.gradle\caches\modules-2\files-2.1\net.java.jinput\jinput-platform\2.0.5\385ee093e01f587f30ee1c8a2ee7d408fd732e16\jinput-platform-2.0.5-natives-windows.jar;C:\Users\sxlga\.gradle\caches\modules-2\files-2.1\net.java.jinput\jinput-platform\2.0.5\53f9c919f34d2ca9de8c51fc4e1e8282029a9232\jinput-platform-2.0.5-natives-osx.jar;C:\Users\sxlga\.gradle\caches\modules-2\files-2.1\tv.twitch\twitch-platform\5.16\7c6affe439099806a4f552da14c42f9d643d8b23\twitch-platform-5.16-natives-windows-32.jar;C:\Users\sxlga\.gradle\caches\modules-2\files-2.1\tv.twitch\twitch-platform\5.16\39d0c3d363735b4785598e0e7fbf8297c706a9f9\twitch-platform-5.16-natives-windows-64.jar;C:\Users\sxlga\.gradle\caches\modules-2\files-2.1\tv.twitch\twitch-platform\5.16\62503ee712766cf77f97252e5902786fd834b8c5\twitch-platform-5.16-natives-osx.jar;C:\Users\sxlga\.gradle\caches\modules-2\files-2.1\tv.twitch\twitch-external-platform\4.5\18215140f010c05b9f86ef6f0f8871954d2ccebf\twitch-external-platform-4.5-natives-windows-32.jar;C:\Users\sxlga\.gradle\caches\modules-2\files-2.1\tv.twitch\twitch-external-platform\4.5\c3cde57891b935d41b6680a9c5e1502eeab76d86\twitch-external-platform-4.5-natives-windows-64.jar;C:\Users\sxlga\.gradle\caches\modules-2\files-2.1\mcp.mobius.waila\Waila\1.5.10_1.7.10\7a874ee79a88cf66bd5355c8393069b3ac39c631\Waila-1.5.10_1.7.10.jar;C:\Users\sxlga\.gradle\caches\modules-2\files-2.1\codechicken\NotEnoughItems\1.7.10-1.0.4.107\fee16ea5f02f8345f9150a528d94348754b56ecf\NotEnoughItems-1.7.10-1.0.4.107-dev.jar;C:\Users\sxlga\.gradle\caches\modules-2\files-2.1\org.lwjgl.lwjgl\lwjgl-platform\2.9.1\4c517eca808522457dd95ee8fc1fbcdbb602efbe\lwjgl-platform-2.9.1-natives-windows.jar;C:\Users\sxlga\.gradle\caches\modules-2\files-2.1\org.lwjgl.lwjgl\lwjgl-platform\2.9.1\aa9aae879af8eb378e22cfc64db56ec2ca9a44d1\lwjgl-platform-2.9.1-natives-linux.jar;C:\Users\sxlga\.gradle\caches\modules-2\files-2.1\org.lwjgl.lwjgl\lwjgl-platform\2.9.1\2d12c83fdfbc04ecabf02c7bc8cc54d034f0daac\lwjgl-platform-2.9.1-natives-osx.jar;C:\Users\sxlga\IdeaProjects\Forge_1.7.10_Template_Schrecktech_Reborn\build\libs\modid-0.0.0-DEV.20200416150316.32fe7ac.jar
[15:03:26] [main/DEBUG] [FML/]: Java library path at launch is C:\Program Files\Java\jdk1.8.0_241\bin;C:\WINDOWS\Sun\Java\bin;C:\WINDOWS\system32;C:\WINDOWS;C:\Program Files (x86)\Common Files\Oracle\Java\javapath;C:\Python27\;C:\Python27\Scripts;C:\Users\sxlga\AppData\Local\Microsoft\WindowsApps;C:\Program Files\Java\jdk-13.0.1\bin;C:\Program Files\doxygen\bin;C:\Program Files\NVIDIA Corporation\NVIDIA NvDLISR;C:\Program Files\nodejs\;C:\ProgramData\chocolatey\bin;C:\Program Files (x86)\Graphviz2.38\bin;C:\Program Files\Microsoft SQL Server\130\Tools\Binn\;C:\Program Files\Microsoft SQL Server\Client SDK\ODBC\170\Tools\Binn\;C:\Program Files\dotnet\;C:\Program Files\PuTTY\;C:\Program Files\Git\cmd;C:\Program Files (x86)\STMicroelectronics\STM32 ST-LINK Utility\ST-LINK Utility;C:\Users\sxlga\AppData\Local\Microsoft\WindowsApps;C:\Users\sxlga\AppData\Roaming\npm;C:\Program Files (x86)\FAHClient;.;C:/Users/sxlga/.gradle/caches/minecraft/net/minecraft/minecraft_natives/1.7.10
[15:03:26] [main/INFO] [FML/]: Managed to load a deobfuscated Minecraft name- we are in a deobfuscated environment. Skipping runtime deobfuscation
[15:03:26] [main/DEBUG] [FML/]: Instantiating coremod class FMLCorePlugin
[15:03:26] [main/DEBUG] [FML/]: Added access transformer class cpw.mods.fml.common.asm.transformers.AccessTransformer to enqueued access transformers
[15:03:26] [main/DEBUG] [FML/]: Enqueued coremod FMLCorePlugin
[15:03:26] [main/DEBUG] [FML/]: Instantiating coremod class FMLForgePlugin
[15:03:26] [main/DEBUG] [FML/]: Added access transformer class net.minecraftforge.transformers.ForgeAccessTransformer to enqueued access transformers
[15:03:26] [main/DEBUG] [FML/]: Enqueued coremod FMLForgePlugin
[15:03:26] [main/DEBUG] [FML/]: All fundamental core mods are successfully located
[15:03:26] [main/INFO] [FML/]: Found a command line coremod : aroma1997.core.coremod.CoreMod
[15:03:26] [main/DEBUG] [FML/]: Instantiating coremod class CoreMod
[15:03:26] [main/WARN] [FML/]: The coremod aroma1997.core.coremod.CoreMod does not have a MCVersion annotation, it may cause issues with this version of Minecraft
[15:03:26] [main/DEBUG] [FML/]: Added access transformer class aroma1997.core.coremod.asm.AromaAccessTransformer to enqueued access transformers
[15:03:26] [main/DEBUG] [FML/]: Enqueued coremod CoreMod
[15:03:26] [main/INFO] [FML/]: Found a command line coremod : codechicken.nei.asm.NEICorePlugin
[15:03:26] [main/DEBUG] [FML/]: Instantiating coremod class NEICorePlugin
[15:03:26] [main/WARN] [FML/]: The coremod codechicken.nei.asm.NEICorePlugin does not have a MCVersion annotation, it may cause issues with this version of Minecraft
[15:03:26] [main/DEBUG] [FML/]: Enqueued coremod NEICorePlugin
[15:03:26] [main/INFO] [FML/]: Found a command line coremod : net.malisis.core.asm.MalisisCorePlugin
[15:03:26] [main/DEBUG] [FML/]: Instantiating coremod class MalisisCorePlugin
[15:03:26] [main/WARN] [FML/]: The coremod net.malisis.core.asm.MalisisCorePlugin does not have a MCVersion annotation, it may cause issues with this version of Minecraft
[15:03:26] [main/DEBUG] [FML/]: Added access transformer class net.malisis.core.asm.MalisisCoreAccessTransformer to enqueued access transformers
[15:03:26] [main/DEBUG] [FML/]: Enqueued coremod MalisisCorePlugin
[15:03:26] [main/INFO] [FML/]: Found a command line coremod : li.cil.oc.common.launch.TransformerLoader
[15:03:26] [main/DEBUG] [FML/]: Instantiating coremod class TransformerLoader
[15:03:26] [main/DEBUG] [FML/]: The coremod li.cil.oc.common.launch.TransformerLoader requested minecraft version 1.7.10 and minecraft is 1.7.10. It will be loaded.
[15:03:26] [main/DEBUG] [FML/]: Enqueued coremod TransformerLoader
[15:03:26] [main/INFO] [FML/]: Found a command line coremod : com.brandon3055.brandonscore.asm.LoadingPlugin
[15:03:26] [main/DEBUG] [FML/]: Instantiating coremod class LoadingPlugin
[15:03:26] [main/TRACE] [FML/]: coremod named Brandon's Core is loading
[15:03:26] [main/DEBUG] [FML/]: The coremod com.brandon3055.brandonscore.asm.LoadingPlugin requested minecraft version 1.7.10 and minecraft is 1.7.10. It will be loaded.
[15:03:26] [main/DEBUG] [FML/]: Enqueued coremod Brandon's Core
[15:03:26] [main/INFO] [FML/]: Found a command line coremod : ic2.core.coremod.IC2core
[15:03:26] [main/DEBUG] [FML/]: Instantiating coremod class IC2core
[15:03:26] [main/WARN] [FML/]: The coremod ic2.core.coremod.IC2core does not have a MCVersion annotation, it may cause issues with this version of Minecraft
[15:03:26] [main/DEBUG] [FML/]: Enqueued coremod IC2core
[15:03:26] [main/INFO] [FML/]: Found a command line coremod : squeek.applecore.AppleCore
[15:03:26] [main/DEBUG] [FML/]: Instantiating coremod class AppleCore
[15:03:26] [main/DEBUG] [FML/]: The coremod squeek.applecore.AppleCore requested minecraft version 1.7.10 and minecraft is 1.7.10. It will be loaded.
[15:03:26] [main/DEBUG] [FML/]: Enqueued coremod AppleCore
[15:03:26] [main/INFO] [FML/]: Found a command line coremod : codechicken.core.launch.CodeChickenCorePlugin
[15:03:26] [main/DEBUG] [FML/]: Instantiating coremod class CodeChickenCorePlugin
[15:03:26] [main/WARN] [FML/]: The coremod codechicken.core.launch.CodeChickenCorePlugin does not have a MCVersion annotation, it may cause issues with this version of Minecraft
[15:03:26] [main/DEBUG] [FML/]: Added access transformer class codechicken.core.asm.CodeChickenAccessTransformer to enqueued access transformers
[15:03:26] [main/DEBUG] [FML/]: Enqueued coremod CodeChickenCorePlugin
[15:03:26] [main/INFO] [FML/]: Found a command line coremod : gtPlusPlus.preloader.asm.Preloader_FMLLoadingPlugin
[15:03:26] [main/DEBUG] [FML/]: Instantiating coremod class Preloader_FMLLoadingPlugin
[15:03:26] [main/DEBUG] [FML/]: The coremod gtPlusPlus.preloader.asm.Preloader_FMLLoadingPlugin requested minecraft version 1.7.10 and minecraft is 1.7.10. It will be loaded.
[15:03:26] [main/DEBUG] [FML/]: Enqueued coremod Preloader_FMLLoadingPlugin
[15:03:26] [main/INFO] [FML/]: Found a command line coremod : farseek.core.FarseekCoreMod
[15:03:26] [main/DEBUG] [FML/]: Instantiating coremod class FarseekCoreMod
[15:03:26] [main/WARN] [FML/]: The coremod farseek.core.FarseekCoreMod does not have a MCVersion annotation, it may cause issues with this version of Minecraft
[15:03:26] [main/DEBUG] [FML/]: Enqueued coremod FarseekCoreMod
[15:03:26] [main/INFO] [FML/]: Found a command line coremod : openblocks.OpenBlocksCorePlugin
[15:03:26] [main/DEBUG] [FML/]: Instantiating coremod class OpenBlocksCorePlugin
[15:03:26] [main/WARN] [FML/]: The coremod openblocks.OpenBlocksCorePlugin does not have a MCVersion annotation, it may cause issues with this version of Minecraft
[15:03:26] [main/DEBUG] [FML/]: Enqueued coremod OpenBlocksCorePlugin
[15:03:26] [main/INFO] [FML/]: Found a command line coremod : invtweaks.forge.asm.FMLPlugin
[15:03:26] [main/DEBUG] [FML/]: Instantiating coremod class FMLPlugin
[15:03:26] [main/WARN] [FML/]: The coremod invtweaks.forge.asm.FMLPlugin does not have a MCVersion annotation, it may cause issues with this version of Minecraft
[15:03:26] [main/DEBUG] [FML/]: Added access transformer class invtweaks.forge.asm.ITAccessTransformer to enqueued access transformers
[15:03:26] [main/DEBUG] [FML/]: Enqueued coremod FMLPlugin
[15:03:26] [main/INFO] [FML/]: Found a command line coremod : net.elnounch.mc.biggerpacketsplz.BiggerPacketsPlzCoreMod
[15:03:26] [main/DEBUG] [FML/]: Instantiating coremod class BiggerPacketsPlzCoreMod
[15:03:26] [main/WARN] [FML/]: The coremod net.elnounch.mc.biggerpacketsplz.BiggerPacketsPlzCoreMod does not have a MCVersion annotation, it may cause issues with this version of Minecraft
[15:03:26] [main/DEBUG] [FML/]: Enqueued coremod BiggerPacketsPlzCoreMod
[15:03:26] [main/INFO] [FML/]: Found a command line coremod : cr0s.warpdrive.core.FMLLoadingPlugin
[15:03:26] [main/DEBUG] [FML/]: Instantiating coremod class FMLLoadingPlugin
[15:03:26] [main/TRACE] [FML/]: coremod named WarpDriveCore is loading
[15:03:26] [main/DEBUG] [FML/]: The coremod cr0s.warpdrive.core.FMLLoadingPlugin requested minecraft version 1.7.10 and minecraft is 1.7.10. It will be loaded.
[15:03:26] [main/DEBUG] [FML/]: Enqueued coremod WarpDriveCore
[15:03:26] [main/INFO] [FML/]: Found a command line coremod : info.inpureprojects.core.Preloader.INpurePreLoader
[15:03:26] [main/DEBUG] [FML/]: Instantiating coremod class INpurePreLoader
[15:03:26] [main/TRACE] [FML/]: coremod named INpurePreLoader is loading
[15:03:26] [main/DEBUG] [FML/]: The coremod info.inpureprojects.core.Preloader.INpurePreLoader requested minecraft version 1.7.10 and minecraft is 1.7.10. It will be loaded.
[15:03:26] [main/DEBUG] [FML/]: Enqueued coremod INpurePreLoader
[15:03:26] [main/INFO] [FML/]: Found a command line coremod : lumien.hardcoredarkness.asm.LoadingPlugin
[15:03:26] [main/DEBUG] [FML/]: Instantiating coremod class LoadingPlugin
[15:03:26] [main/WARN] [FML/]: The coremod lumien.hardcoredarkness.asm.LoadingPlugin does not have a MCVersion annotation, it may cause issues with this version of Minecraft
[15:03:26] [main/DEBUG] [FML/]: Enqueued coremod LoadingPlugin
[15:03:26] [main/INFO] [FML/]: Found a command line coremod : codechicken.core.launch.DepLoader
[15:03:26] [main/DEBUG] [FML/]: Instantiating coremod class DepLoader
[15:03:26] [main/WARN] [FML/]: The coremod codechicken.core.launch.DepLoader does not have a MCVersion annotation, it may cause issues with this version of Minecraft
[15:03:26] [main/DEBUG] [FML/]: Enqueued coremod DepLoader
[15:03:26] [main/INFO] [FML/]: Found a command line coremod : net.blay09.mods.craftingtweaks.coremod.CraftingTweaksLoadingPlugin
[15:03:26] [main/DEBUG] [FML/]: Instantiating coremod class CraftingTweaksLoadingPlugin
[15:03:26] [main/TRACE] [FML/]: coremod named CraftingTweaks is loading
[15:03:26] [main/DEBUG] [FML/]: The coremod net.blay09.mods.craftingtweaks.coremod.CraftingTweaksLoadingPlugin requested minecraft version 1.7.10 and minecraft is 1.7.10. It will be loaded.
[15:03:26] [main/DEBUG] [FML/]: Enqueued coremod CraftingTweaks
[15:03:26] [main/INFO] [FML/]: Found a command line coremod : appeng.transformer.AppEngCore
[15:03:26] [main/DEBUG] [FML/]: Instantiating coremod class AppEngCore
[15:03:26] [main/DEBUG] [FML/]: The coremod appeng.transformer.AppEngCore requested minecraft version 1.7.10 and minecraft is 1.7.10. It will be loaded.
[15:03:26] [main/INFO] [FML/]: [AppEng] Core Init
[15:03:26] [main/DEBUG] [FML/]: Added access transformer class appeng.transformer.asm.ASMTweaker to enqueued access transformers
[15:03:26] [main/DEBUG] [FML/]: Enqueued coremod AppEngCore
[15:03:26] [main/INFO] [FML/]: Found a command line coremod : openmods.core.OpenModsCorePlugin
[15:03:26] [main/DEBUG] [FML/]: Instantiating coremod class OpenModsCorePlugin
[15:03:26] [main/WARN] [FML/]: The coremod openmods.core.OpenModsCorePlugin does not have a MCVersion annotation, it may cause issues with this version of Minecraft
[15:03:26] [main/DEBUG] [OpenMods/]: openmods.core.OpenModsCorePlugin.<init>(OpenModsCorePlugin.java:18): <OpenModsLib 0.10>\o
[15:03:26] [main/DEBUG] [FML/]: Enqueued coremod OpenModsCorePlugin
[15:03:26] [main/DEBUG] [FML/]: Attempting to load commandline specified mods, relative to C:\Users\sxlga\IdeaProjects\Forge_1.7.10_Template_Schrecktech_Reborn\.minecraft\.
[15:03:26] [main/DEBUG] [FML/]: Discovering coremods
[15:03:26] [main/INFO] [LaunchWrapper/]: Calling tweak class net.minecraftforge.gradle.tweakers.CoremodTweaker
[15:03:26] [main/INFO] [GradleStart/]: Injecting location in coremod cpw.mods.fml.relauncher.FMLCorePlugin
[15:03:26] [main/INFO] [GradleStart/]: Injecting location in coremod net.minecraftforge.classloading.FMLForgePlugin
[15:03:26] [main/INFO] [GradleStart/]: Injecting location in coremod codechicken.core.asm.MCPDeobfuscationTransformer.LoadPlugin
[15:03:26] [main/INFO] [GradleStart/]: Injecting location in coremod aroma1997.core.coremod.CoreMod
[15:03:26] [main/INFO] [GradleStart/]: Injecting location in coremod codechicken.nei.asm.NEICorePlugin
[15:03:26] [main/INFO] [GradleStart/]: Injecting location in coremod net.malisis.core.asm.MalisisCorePlugin
[15:03:26] [main/INFO] [GradleStart/]: Injecting location in coremod li.cil.oc.common.launch.TransformerLoader
[15:03:26] [main/INFO] [GradleStart/]: Injecting location in coremod com.brandon3055.brandonscore.asm.LoadingPlugin
[15:03:26] [main/INFO] [GradleStart/]: Injecting location in coremod ic2.core.coremod.IC2core
[15:03:26] [main/INFO] [GradleStart/]: Injecting location in coremod squeek.applecore.AppleCore
[15:03:26] [main/INFO] [GradleStart/]: Injecting location in coremod codechicken.core.launch.CodeChickenCorePlugin
[15:03:26] [main/INFO] [GradleStart/]: Injecting location in coremod gtPlusPlus.preloader.asm.Preloader_FMLLoadingPlugin
[15:03:26] [main/INFO] [GradleStart/]: Injecting location in coremod farseek.core.FarseekCoreMod
[15:03:26] [main/INFO] [GradleStart/]: Injecting location in coremod openblocks.OpenBlocksCorePlugin
[15:03:26] [main/INFO] [GradleStart/]: Injecting location in coremod invtweaks.forge.asm.FMLPlugin
[15:03:26] [main/INFO] [GradleStart/]: Injecting location in coremod net.elnounch.mc.biggerpacketsplz.BiggerPacketsPlzCoreMod
[15:03:26] [main/INFO] [GradleStart/]: Injecting location in coremod cr0s.warpdrive.core.FMLLoadingPlugin
[15:03:26] [main/INFO] [GradleStart/]: Injecting location in coremod info.inpureprojects.core.Preloader.INpurePreLoader
[15:03:26] [main/INFO] [GradleStart/]: Injecting location in coremod lumien.hardcoredarkness.asm.LoadingPlugin
[15:03:26] [main/INFO] [GradleStart/]: Injecting location in coremod codechicken.core.launch.DepLoader
[15:03:26] [main/INFO] [GradleStart/]: Injecting location in coremod net.blay09.mods.craftingtweaks.coremod.CraftingTweaksLoadingPlugin
[15:03:26] [main/INFO] [GradleStart/]: Injecting location in coremod appeng.transformer.AppEngCore
[15:03:26] [main/INFO] [GradleStart/]: Injecting location in coremod openmods.core.OpenModsCorePlugin
[15:03:26] [main/INFO] [LaunchWrapper/]: Loading tweak class name cpw.mods.fml.common.launcher.FMLInjectionAndSortingTweaker
[15:03:26] [main/INFO] [LaunchWrapper/]: Loading tweak class name cpw.mods.fml.common.launcher.FMLDeobfTweaker
[15:03:26] [main/INFO] [LaunchWrapper/]: Loading tweak class name net.minecraftforge.gradle.tweakers.AccessTransformerTweaker
[15:03:26] [main/INFO] [LaunchWrapper/]: Calling tweak class cpw.mods.fml.common.launcher.FMLInjectionAndSortingTweaker
[15:03:26] [main/INFO] [LaunchWrapper/]: Calling tweak class cpw.mods.fml.common.launcher.FMLInjectionAndSortingTweaker
[15:03:26] [main/INFO] [LaunchWrapper/]: Calling tweak class cpw.mods.fml.relauncher.CoreModManager$FMLPluginWrapper
[15:03:26] [main/DEBUG] [FML/]: Injecting coremod FMLCorePlugin {cpw.mods.fml.relauncher.FMLCorePlugin} class transformers
[15:03:26] [main/TRACE] [FML/]: Registering transformer cpw.mods.fml.common.asm.transformers.MarkerTransformer
[15:03:26] [main/TRACE] [FML/]: Registering transformer cpw.mods.fml.common.asm.transformers.SideTransformer
[15:03:26] [main/TRACE] [FML/]: Registering transformer cpw.mods.fml.common.asm.transformers.EventSubscriptionTransformer
[15:03:26] [main/DEBUG] [FML/]: Injection complete
[15:03:26] [main/DEBUG] [FML/]: Running coremod plugin for FMLCorePlugin {cpw.mods.fml.relauncher.FMLCorePlugin}
[15:03:26] [main/DEBUG] [FML/]: Running coremod plugin FMLCorePlugin
[15:03:26] [main/ERROR] [FML/]: The binary patch set is missing. Either you are in a development environment, or things are not going to work!
[15:03:28] [main/ERROR] [FML/]: FML appears to be missing any signature data. This is not a good thing
[15:03:28] [main/DEBUG] [FML/]: Coremod plugin class FMLCorePlugin run successfully
[15:03:28] [main/INFO] [LaunchWrapper/]: Calling tweak class cpw.mods.fml.relauncher.CoreModManager$FMLPluginWrapper
[15:03:28] [main/DEBUG] [FML/]: Injecting coremod FMLForgePlugin {net.minecraftforge.classloading.FMLForgePlugin} class transformers
[15:03:28] [main/TRACE] [FML/]: Registering transformer net.minecraftforge.classloading.FluidIdTransformer
[15:03:28] [main/DEBUG] [FML/]: Injection complete
[15:03:28] [main/DEBUG] [FML/]: Running coremod plugin for FMLForgePlugin {net.minecraftforge.classloading.FMLForgePlugin}
[15:03:28] [main/DEBUG] [FML/]: Running coremod plugin FMLForgePlugin
[15:03:28] [main/DEBUG] [FML/]: Coremod plugin class FMLForgePlugin run successfully
[15:03:28] [main/INFO] [LaunchWrapper/]: Calling tweak class cpw.mods.fml.relauncher.CoreModManager$FMLPluginWrapper
[15:03:28] [main/DEBUG] [FML/]: Injecting coremod CCCDeobfPlugin {codechicken.core.asm.MCPDeobfuscationTransformer$LoadPlugin} class transformers
[15:03:28] [main/DEBUG] [FML/]: Injection complete
[15:03:28] [main/DEBUG] [FML/]: Running coremod plugin for CCCDeobfPlugin {codechicken.core.asm.MCPDeobfuscationTransformer$LoadPlugin}
[15:03:28] [main/DEBUG] [FML/]: Running coremod plugin CCCDeobfPlugin
[15:03:28] [main/DEBUG] [FML/]: Coremod plugin class LoadPlugin run successfully
[15:03:28] [main/INFO] [LaunchWrapper/]: Calling tweak class cpw.mods.fml.relauncher.CoreModManager$FMLPluginWrapper
[15:03:28] [main/DEBUG] [FML/]: Injecting coremod CoreMod {aroma1997.core.coremod.CoreMod} class transformers
[15:03:28] [main/DEBUG] [FML/]: Injection complete
[15:03:28] [main/DEBUG] [FML/]: Running coremod plugin for CoreMod {aroma1997.core.coremod.CoreMod}
[15:03:28] [main/DEBUG] [FML/]: Running coremod plugin CoreMod
[15:03:28] [main/INFO] [Aroma1997Core/]: Finished data injection.
[15:03:28] [main/INFO] [Aroma1997Core/]: Finished data injection.
[15:03:28] [main/TRACE] [Aroma1997Core/]: Initializing Configurations from: .\config
[15:03:28] [main/DEBUG] [FML/]: Coremod plugin class CoreMod run successfully
[15:03:28] [main/INFO] [LaunchWrapper/]: Calling tweak class cpw.mods.fml.relauncher.CoreModManager$FMLPluginWrapper
[15:03:28] [main/DEBUG] [FML/]: Injecting coremod NEICorePlugin {codechicken.nei.asm.NEICorePlugin} class transformers
[15:03:28] [main/TRACE] [FML/]: Registering transformer codechicken.nei.asm.NEITransformer
[15:03:28] [main/DEBUG] [FML/]: Injection complete
[15:03:28] [main/DEBUG] [FML/]: Running coremod plugin for NEICorePlugin {codechicken.nei.asm.NEICorePlugin}
[15:03:28] [main/DEBUG] [FML/]: Running coremod plugin NEICorePlugin
[15:03:28] [main/DEBUG] [FML/]: Coremod plugin class NEICorePlugin run successfully
[15:03:28] [main/INFO] [LaunchWrapper/]: Calling tweak class cpw.mods.fml.relauncher.CoreModManager$FMLPluginWrapper
[15:03:28] [main/DEBUG] [FML/]: Injecting coremod TransformerLoader {li.cil.oc.common.launch.TransformerLoader} class transformers
[15:03:28] [main/TRACE] [FML/]: Registering transformer li.cil.oc.common.asm.ClassTransformer
[15:03:28] [main/DEBUG] [FML/]: Injection complete
[15:03:28] [main/DEBUG] [FML/]: Running coremod plugin for TransformerLoader {li.cil.oc.common.launch.TransformerLoader}
[15:03:28] [main/DEBUG] [FML/]: Running coremod plugin TransformerLoader
[15:03:28] [main/DEBUG] [FML/]: Coremod plugin class TransformerLoader run successfully
[15:03:28] [main/INFO] [LaunchWrapper/]: Calling tweak class cpw.mods.fml.relauncher.CoreModManager$FMLPluginWrapper
[15:03:28] [main/DEBUG] [FML/]: Injecting coremod IC2core {ic2.core.coremod.IC2core} class transformers
[15:03:28] [main/DEBUG] [FML/]: Injection complete
[15:03:28] [main/DEBUG] [FML/]: Running coremod plugin for IC2core {ic2.core.coremod.IC2core}
[15:03:28] [main/DEBUG] [FML/]: Running coremod plugin IC2core
[15:03:28] [main/INFO] [IC2-core/]: Loaded library EJML-core-0.26.jar.
[15:03:28] [main/DEBUG] [FML/]: Coremod plugin class IC2core run successfully
[15:03:28] [main/INFO] [LaunchWrapper/]: Calling tweak class cpw.mods.fml.relauncher.CoreModManager$FMLPluginWrapper
[15:03:28] [main/DEBUG] [FML/]: Injecting coremod CodeChickenCorePlugin {codechicken.core.launch.CodeChickenCorePlugin} class transformers
[15:03:28] [main/TRACE] [FML/]: Registering transformer codechicken.lib.asm.ClassHeirachyManager
[15:03:28] [main/TRACE] [FML/]: Registering transformer codechicken.core.asm.InterfaceDependancyTransformer
[15:03:28] [main/TRACE] [FML/]: Registering transformer codechicken.core.asm.TweakTransformer
[15:03:28] [main/TRACE] [FML/]: Registering transformer codechicken.core.asm.DelegatedTransformer
[15:03:28] [main/TRACE] [FML/]: Registering transformer codechicken.core.asm.DefaultImplementationTransformer
[15:03:28] [main/DEBUG] [FML/]: Injection complete
[15:03:28] [main/DEBUG] [FML/]: Running coremod plugin for CodeChickenCorePlugin {codechicken.core.launch.CodeChickenCorePlugin}
[15:03:28] [main/DEBUG] [FML/]: Running coremod plugin CodeChickenCorePlugin
[15:03:28] [main/DEBUG] [FML/]: Coremod plugin class CodeChickenCorePlugin run successfully
[15:03:28] [main/INFO] [LaunchWrapper/]: Calling tweak class cpw.mods.fml.relauncher.CoreModManager$FMLPluginWrapper
[15:03:28] [main/DEBUG] [FML/]: Injecting coremod FMLPlugin {invtweaks.forge.asm.FMLPlugin} class transformers
[15:03:28] [main/TRACE] [FML/]: Registering transformer invtweaks.forge.asm.ContainerTransformer
[15:03:28] [main/DEBUG] [FML/]: Injection complete
[15:03:28] [main/DEBUG] [FML/]: Running coremod plugin for FMLPlugin {invtweaks.forge.asm.FMLPlugin}
[15:03:28] [main/DEBUG] [FML/]: Running coremod plugin FMLPlugin
[15:03:28] [main/DEBUG] [FML/]: Coremod plugin class FMLPlugin run successfully
[15:03:28] [main/INFO] [LaunchWrapper/]: Calling tweak class cpw.mods.fml.relauncher.CoreModManager$FMLPluginWrapper
[15:03:28] [main/DEBUG] [FML/]: Injecting coremod BiggerPacketsPlzCoreMod {net.elnounch.mc.biggerpacketsplz.BiggerPacketsPlzCoreMod} class transformers
[15:03:28] [main/TRACE] [FML/]: Registering transformer net.elnounch.mc.biggerpacketsplz.BiggerPacketsPlzClassTransformer
[15:03:28] [main/DEBUG] [biggerpacketsplz.ClassTransformer/]: Looking for mcVersion
[15:03:28] [main/DEBUG] [biggerpacketsplz.ClassTransformer/]: Detected mcVersion '1.7.10'
[15:03:28] [main/DEBUG] [biggerpacketsplz.ClassTransformer/]: Will look after classes : {net.minecraft.network.PacketBuffer={readNBTTagCompoundFromBuffer=[()Lnet/minecraft/nbt/NBTTagCompound;]}, et={b=[()Ldh;]}}
[15:03:28] [main/DEBUG] [biggerpacketsplz.ClassTransformer/]: Will look after values : {2097152=16777216, 2097152=16777216}
[15:03:28] [main/DEBUG] [FML/]: Injection complete
[15:03:28] [main/DEBUG] [FML/]: Running coremod plugin for BiggerPacketsPlzCoreMod {net.elnounch.mc.biggerpacketsplz.BiggerPacketsPlzCoreMod}
[15:03:28] [main/DEBUG] [FML/]: Running coremod plugin BiggerPacketsPlzCoreMod
[15:03:28] [main/DEBUG] [FML/]: Coremod plugin class BiggerPacketsPlzCoreMod run successfully
[15:03:28] [main/INFO] [LaunchWrapper/]: Calling tweak class cpw.mods.fml.relauncher.CoreModManager$FMLPluginWrapper
[15:03:28] [main/DEBUG] [FML/]: Injecting coremod INpurePreLoader {info.inpureprojects.core.Preloader.INpurePreLoader} class transformers
[15:03:28] [main/DEBUG] [FML/]: Injection complete
[15:03:28] [main/DEBUG] [FML/]: Running coremod plugin for INpurePreLoader {info.inpureprojects.core.Preloader.INpurePreLoader}
[15:03:28] [main/DEBUG] [FML/]: Running coremod plugin INpurePreLoader
[15:03:28] [main/INFO] [INpurePreloader/]: Attempting to detect JVM version...
[15:03:28] [main/INFO] [INpurePreloader/]: Detected JVM: 1.8
[15:03:28] [main/INFO] [INpurePreloader/]: We are in dev mode!
[15:03:28] [main/INFO] [INpurePreloader/]: Starting library configuration...
[15:03:28] [main/INFO] [INpureLogInterceptor/]: System attached to FML. Now intercepting all logging calls.
[15:03:28] [main/DEBUG] [FML/]: Coremod plugin class INpurePreLoader run successfully
[15:03:28] [main/INFO] [LaunchWrapper/]: Calling tweak class cpw.mods.fml.relauncher.CoreModManager$FMLPluginWrapper
[15:03:28] [main/DEBUG] [FML/]: Injecting coremod DepLoader {codechicken.core.launch.DepLoader} class transformers
[15:03:28] [main/DEBUG] [FML/]: Injection complete
[15:03:28] [main/DEBUG] [FML/]: Running coremod plugin for DepLoader {codechicken.core.launch.DepLoader}
[15:03:28] [main/DEBUG] [FML/]: Running coremod plugin DepLoader
[15:03:28] [main/DEBUG] [FML/]: Coremod plugin class DepLoader run successfully
[15:03:28] [main/INFO] [LaunchWrapper/]: Calling tweak class cpw.mods.fml.relauncher.CoreModManager$FMLPluginWrapper
[15:03:28] [main/DEBUG] [FML/]: Injecting coremod AppEngCore {appeng.transformer.AppEngCore} class transformers
[15:03:28] [main/TRACE] [FML/]: Registering transformer appeng.transformer.asm.ASMIntegration
[15:03:28] [main/DEBUG] [FML/]: Injection complete
[15:03:28] [main/DEBUG] [FML/]: Running coremod plugin for AppEngCore {appeng.transformer.AppEngCore}
[15:03:28] [main/DEBUG] [FML/]: Running coremod plugin AppEngCore
[15:03:28] [main/DEBUG] [FML/]: Coremod plugin class AppEngCore run successfully
[15:03:28] [main/INFO] [LaunchWrapper/]: Calling tweak class cpw.mods.fml.relauncher.CoreModManager$FMLPluginWrapper
[15:03:28] [main/DEBUG] [FML/]: Injecting coremod OpenModsCorePlugin {openmods.core.OpenModsCorePlugin} class transformers
[15:03:28] [main/TRACE] [FML/]: Registering transformer openmods.core.OpenModsClassTransformer
[15:03:28] [main/DEBUG] [FML/]: Injection complete
[15:03:28] [main/DEBUG] [FML/]: Running coremod plugin for OpenModsCorePlugin {openmods.core.OpenModsCorePlugin}
[15:03:28] [main/DEBUG] [FML/]: Running coremod plugin OpenModsCorePlugin
[15:03:28] [main/DEBUG] [OpenMods/]: openmods.config.simple.ConfigProcessor.process(ConfigProcessor.java:83): Parsing config file '.\config\OpenModsLibCore.json'
[15:03:29] [main/TRACE] [OpenMods/]: openmods.utils.StateTracker$StateUpdater.update(StateTracker.java:26): State of gl_capabilities_hook updated from DISABLED to ENABLED
[15:03:29] [main/TRACE] [OpenMods/]: openmods.utils.StateTracker$StateUpdater.update(StateTracker.java:26): State of player_render_hook updated from DISABLED to ENABLED
[15:03:29] [main/TRACE] [OpenMods/]: openmods.utils.StateTracker$StateUpdater.update(StateTracker.java:26): State of map_gen_fix updated from DISABLED to ENABLED
[15:03:29] [main/TRACE] [OpenMods/]: openmods.utils.StateTracker$StateUpdater.update(StateTracker.java:26): State of player_damage_hook updated from DISABLED to ENABLED
[15:03:29] [main/TRACE] [OpenMods/]: openmods.utils.StateTracker$StateUpdater.update(StateTracker.java:26): State of movement_callback updated from DISABLED to ENABLED
[15:03:29] [main/TRACE] [OpenMods/]: openmods.utils.StateTracker$StateUpdater.update(StateTracker.java:26): State of stencil_patches updated from DISABLED to ENABLED
[15:03:29] [main/DEBUG] [FML/]: Coremod plugin class OpenModsCorePlugin run successfully
[15:03:29] [main/INFO] [LaunchWrapper/]: Calling tweak class cpw.mods.fml.relauncher.CoreModManager$FMLPluginWrapper
[15:03:29] [main/DEBUG] [FML/]: Injecting coremod OpenBlocksCorePlugin {openblocks.OpenBlocksCorePlugin} class transformers
[15:03:29] [main/TRACE] [FML/]: Registering transformer openblocks.asm.OpenBlocksClassTransformer
[15:03:29] [main/DEBUG] [FML/]: Injection complete
[15:03:29] [main/DEBUG] [FML/]: Running coremod plugin for OpenBlocksCorePlugin {openblocks.OpenBlocksCorePlugin}
[15:03:29] [main/DEBUG] [FML/]: Running coremod plugin OpenBlocksCorePlugin
[15:03:29] [main/DEBUG] [FML/]: Coremod plugin class OpenBlocksCorePlugin run successfully
[15:03:29] [main/INFO] [LaunchWrapper/]: Calling tweak class cpw.mods.fml.common.launcher.FMLDeobfTweaker
[15:03:29] [main/DEBUG] [FML/]: Loaded 57 rules from AccessTransformer config file fml_at.cfg
[15:03:29] [main/DEBUG] [FML/]: Loaded 89 rules from AccessTransformer config file forge_at.cfg
[15:03:29] [main/DEBUG] [FML/]: Loaded 6 rules from AccessTransformer config file aroma1997core_at.cfg
[15:03:29] [main/DEBUG] [FML/]: Loaded 5 rules from AccessTransformer config file malisiscore_at.cfg
[15:03:29] [main/DEBUG] [FML/]: Loaded 57 rules from AccessTransformer config file fml_at.cfg
[15:03:29] [main/DEBUG] [FML/]: Loaded 9 rules from AccessTransformer config file invtweaks_at.cfg
[15:03:29] [main/DEBUG] [FML/]: Loaded 11 rules from AccessTransformer mod jar file C:\Users\sxlga\.gradle\caches\modules-2\files-2.1\curse.maven\NotEnoughItems-1.7.10-2.0.1-GTNH-universal\2906319\e222ef0b95bab25b0c7f8fdee5c0e46cbba2ffbc\NotEnoughItems-1.7.10-2.0.1-GTNH-universal-2906319.jar!META-INF/nei_at.cfg

[15:03:29] [main/DEBUG] [FML/]: Loaded 8 rules from AccessTransformer mod jar file C:\Users\sxlga\.gradle\caches\modules-2\files-2.1\li.cil.oc\OpenComputers\MC1.7.10-1.7.2.1204\23ea8e10318530e74a6a845d8743a6ad0238c00\OpenComputers-MC1.7.10-1.7.2.1204-dev.jar!META-INF/oc_at.cfg

[15:03:29] [main/DEBUG] [FML/]: Loaded 10 rules from AccessTransformer mod jar file C:\Users\sxlga\.gradle\caches\modules-2\files-2.1\curse.maven\AIImprovements-1.7.10-0.0.1b19-dev\2252676\2c34459174f9e9b03569a7958cdf6e01a6ba49c4\AIImprovements-1.7.10-0.0.1b19-dev-2252676.jar!META-INF/AI_at.cfg

[15:03:29] [main/DEBUG] [FML/]: Loaded 5 rules from AccessTransformer mod jar file C:\Users\sxlga\.gradle\caches\modules-2\files-2.1\farseek\Farseek\1.7.10\615e8b0a93f083a50ac1f6d703d4ddf8bc269446\Farseek-1.7.10-2.0.1.jar!META-INF/farseek_at.cfg

[15:03:29] [main/DEBUG] [FML/]: Loaded 60 rules from AccessTransformer mod jar file C:\Users\sxlga\.gradle\caches\modules-2\files-2.1\ichunutil\iChunUtil\4.2.3\4e3eb786d262e58ae6f8d9921fe50aff7ad4f7a3\iChunUtil-4.2.3-deobf.jar!META-INF/iChunUtil-deobf_at.cfg

[15:03:29] [main/DEBUG] [FML/]: Loaded 11 rules from AccessTransformer mod jar file C:\Users\sxlga\.gradle\caches\modules-2\files-2.1\codechicken\NotEnoughItems\1.7.10-1.0.4.107\fee16ea5f02f8345f9150a528d94348754b56ecf\NotEnoughItems-1.7.10-1.0.4.107-dev.jar!META-INF/nei_at.cfg

[15:03:29] [main/DEBUG] [FML/]: Loaded 1 rules from AccessTransformer mod jar file C:\Users\sxlga\.gradle\caches\modules-2\files-2.1\curse.maven\INpureCore-[1.7.10]1.0.0B9-62\2238507\83e774abd91fa98e4ee809d724085116d0e155b6\INpureCore-[1.7.10]1.0.0B9-62-2238507.jar!META-INF/inpure_at.cfg

[15:03:29] [main/DEBUG] [FML/]: Loaded 62 rules from AccessTransformer mod jar file C:\Users\sxlga\.gradle\caches\modules-2\files-2.1\curse.maven\WarpDrive-1.7.10-1.4.2\2578306\fbcf32d155a90a4d79c6185094c0790631bef22d\WarpDrive-1.7.10-1.4.2-2578306.jar!META-INF/WarpDrive_at.cfg

[15:03:29] [main/DEBUG] [FML/]: Loaded 7 rules from AccessTransformer mod jar file C:\Users\sxlga\.gradle\caches\modules-2\files-2.1\crafting-tweaks\craftingtweaks\mc1.7.10\9b4ff8b2c59cc78ba45c1d648cbd23ad01c53d45\craftingtweaks-mc1.7.10-1.0.88.jar!META-INF/craftingtweaks_at.cfg

[15:03:29] [main/DEBUG] [FML/]: Loaded 2 rules from AccessTransformer mod jar file C:\Users\sxlga\.gradle\caches\modules-2\files-2.1\streams\Streams\1.7.10\9ead1486d85c1bf120ddd7fc284ff2091b3d9f61\Streams-1.7.10-0.3.4.jar!META-INF/streams_at.cfg

[15:03:29] [main/DEBUG] [FML/]: Loaded 3 rules from AccessTransformer mod jar file C:\Users\sxlga\.gradle\caches\modules-2\files-2.1\netherportalfix\netherportalfix\mc1.7.10\c812e8edc89718fd1ecc5d6bdb0855a0ac4f62f1\netherportalfix-mc1.7.10-1.1.0.jar!META-INF/netherportalfix_at.cfg

[15:03:29] [main/DEBUG] [FML/]: Loaded 31 rules from AccessTransformer mod jar file C:\Users\sxlga\.gradle\caches\modules-2\files-2.1\tinkers-construct\TConstruct\1.7.10\35e7ee78cd1f8b185373a6b91de252fa14755f3f\TConstruct-1.7.10-1.8.8.build991.jar!META-INF/TConstruct_at.cfg

[15:03:29] [main/DEBUG] [FML/]: Validating minecraft
[15:03:29] [main/DEBUG] [FML/]: Minecraft validated, launching...
[15:03:29] [main/INFO] [LaunchWrapper/]: Calling tweak class cpw.mods.fml.relauncher.CoreModManager$FMLPluginWrapper
[15:03:29] [main/DEBUG] [FML/]: Injecting coremod MalisisCorePlugin {net.malisis.core.asm.MalisisCorePlugin} class transformers
[15:03:29] [main/TRACE] [FML/]: Registering transformer net.malisis.core.util.chunkcollision.ChunkCollisionTransformer
[15:03:29] [main/INFO] [malisiscore/]: [ChunkCollisionTransformer] Hook registered for net.minecraft.world.World
[15:03:29] [main/INFO] [malisiscore/]: [ChunkCollisionTransformer] Hook registered for net.minecraft.world.World
[15:03:29] [main/INFO] [malisiscore/]: [ChunkCollisionTransformer] Hook registered for net.minecraft.item.ItemBlock
[15:03:29] [main/INFO] [malisiscore/]: [ChunkCollisionTransformer] Hook registered for net.minecraft.network.NetHandlerPlayServer
[15:03:29] [main/TRACE] [FML/]: Registering transformer net.malisis.core.util.chunkblock.ChunkBlockTransformer
[15:03:29] [main/INFO] [malisiscore/]: [ChunkBlockTransformer] Hook registered for net.minecraft.world.chunk.Chunk
[15:03:29] [main/DEBUG] [FML/]: Injection complete
[15:03:29] [main/DEBUG] [FML/]: Running coremod plugin for MalisisCorePlugin {net.malisis.core.asm.MalisisCorePlugin}
[15:03:29] [main/DEBUG] [FML/]: Running coremod plugin MalisisCorePlugin
[15:03:29] [main/DEBUG] [FML/]: Coremod plugin class MalisisCorePlugin run successfully
[15:03:29] [main/INFO] [LaunchWrapper/]: Calling tweak class cpw.mods.fml.relauncher.CoreModManager$FMLPluginWrapper
[15:03:29] [main/DEBUG] [FML/]: Injecting coremod Brandon's Core {com.brandon3055.brandonscore.asm.LoadingPlugin} class transformers
[15:03:29] [main/TRACE] [FML/]: Registering transformer com.brandon3055.brandonscore.asm.ClassTransformer
[15:03:29] [main/DEBUG] [FML/]: Injection complete
[15:03:29] [main/DEBUG] [FML/]: Running coremod plugin for Brandon's Core {com.brandon3055.brandonscore.asm.LoadingPlugin}
[15:03:29] [main/DEBUG] [FML/]: Running coremod plugin Brandon's Core
[15:03:29] [main/DEBUG] [FML/]: Coremod plugin class LoadingPlugin run successfully
[15:03:29] [main/INFO] [LaunchWrapper/]: Calling tweak class cpw.mods.fml.relauncher.CoreModManager$FMLPluginWrapper
[15:03:29] [main/DEBUG] [FML/]: Injecting coremod WarpDriveCore {cr0s.warpdrive.core.FMLLoadingPlugin} class transformers
[15:03:29] [main/TRACE] [FML/]: Registering transformer cr0s.warpdrive.core.ClassTransformer
[15:03:29] [main/DEBUG] [FML/]: Injection complete
[15:03:29] [main/DEBUG] [FML/]: Running coremod plugin for WarpDriveCore {cr0s.warpdrive.core.FMLLoadingPlugin}
[15:03:29] [main/DEBUG] [FML/]: Running coremod plugin WarpDriveCore
[15:03:29] [main/DEBUG] [FML/]: Coremod plugin class FMLLoadingPlugin run successfully
[15:03:29] [main/INFO] [LaunchWrapper/]: Calling tweak class cpw.mods.fml.relauncher.CoreModManager$FMLPluginWrapper
[15:03:29] [main/DEBUG] [FML/]: Injecting coremod LoadingPlugin {lumien.hardcoredarkness.asm.LoadingPlugin} class transformers
[15:03:29] [main/TRACE] [FML/]: Registering transformer lumien.hardcoredarkness.asm.ClassTransformer
[15:03:29] [main/DEBUG] [FML/]: Injection complete
[15:03:29] [main/DEBUG] [FML/]: Running coremod plugin for LoadingPlugin {lumien.hardcoredarkness.asm.LoadingPlugin}
[15:03:29] [main/DEBUG] [FML/]: Running coremod plugin LoadingPlugin
[15:03:29] [main/DEBUG] [FML/]: Coremod plugin class LoadingPlugin run successfully
[15:03:29] [main/INFO] [LaunchWrapper/]: Calling tweak class cpw.mods.fml.relauncher.CoreModManager$FMLPluginWrapper
[15:03:29] [main/DEBUG] [FML/]: Injecting coremod CraftingTweaks {net.blay09.mods.craftingtweaks.coremod.CraftingTweaksLoadingPlugin} class transformers
[15:03:29] [main/TRACE] [FML/]: Registering transformer net.blay09.mods.craftingtweaks.coremod.GuiScreenClassTransformer
[15:03:29] [main/DEBUG] [FML/]: Injection complete
[15:03:29] [main/DEBUG] [FML/]: Running coremod plugin for CraftingTweaks {net.blay09.mods.craftingtweaks.coremod.CraftingTweaksLoadingPlugin}
[15:03:29] [main/DEBUG] [FML/]: Running coremod plugin CraftingTweaks
[15:03:29] [main/DEBUG] [FML/]: Coremod plugin class CraftingTweaksLoadingPlugin run successfully
[15:03:29] [main/INFO] [LaunchWrapper/]: Calling tweak class net.minecraftforge.gradle.tweakers.AccessTransformerTweaker
[15:03:29] [main/DEBUG] [GradleStart/]: Reading CSV file: C:\Users\sxlga\.gradle\caches\minecraft\de\oceanlabs\mcp\mcp_stable\12\fields.csv
[15:03:29] [main/DEBUG] [GradleStart/]: Reading CSV file: C:\Users\sxlga\.gradle\caches\minecraft\de\oceanlabs\mcp\mcp_stable\12\methods.csv
[15:03:29] [main/INFO] [GradleStart/]: Remapping AccessTransformer rules...
[15:03:29] [main/INFO] [LaunchWrapper/]: Calling tweak class cpw.mods.fml.relauncher.CoreModManager$FMLPluginWrapper
[15:03:29] [main/DEBUG] [FML/]: Injecting coremod AppleCore {squeek.applecore.AppleCore} class transformers
[15:03:29] [main/TRACE] [FML/]: Registering transformer squeek.applecore.asm.TransformerModuleHandler
[15:03:29] [main/DEBUG] [FML/]: Injection complete
[15:03:29] [main/DEBUG] [FML/]: Running coremod plugin for AppleCore {squeek.applecore.AppleCore}
[15:03:29] [main/DEBUG] [FML/]: Running coremod plugin AppleCore
[15:03:29] [main/DEBUG] [FML/]: Coremod plugin class AppleCore run successfully
[15:03:29] [main/INFO] [LaunchWrapper/]: Calling tweak class cpw.mods.fml.relauncher.CoreModManager$FMLPluginWrapper
[15:03:29] [main/DEBUG] [FML/]: Injecting coremod FarseekCoreMod {farseek.core.FarseekCoreMod} class transformers
[15:03:29] [main/TRACE] [FML/]: Registering transformer farseek.core.FarseekClassTransformer
[15:03:29] [main/DEBUG] [FML/]: Injection complete
[15:03:29] [main/DEBUG] [FML/]: Running coremod plugin for FarseekCoreMod {farseek.core.FarseekCoreMod}
[15:03:29] [main/DEBUG] [FML/]: Running coremod plugin FarseekCoreMod
[15:03:29] [main/DEBUG] [FML/]: Coremod plugin class FarseekCoreMod run successfully
[15:03:29] [main/INFO] [LaunchWrapper/]: Calling tweak class cpw.mods.fml.relauncher.CoreModManager$FMLPluginWrapper
[15:03:29] [main/DEBUG] [FML/]: Injecting coremod Preloader_FMLLoadingPlugin {gtPlusPlus.preloader.asm.Preloader_FMLLoadingPlugin} class transformers
[15:03:29] [main/DEBUG] [farseek.farseek/]: Found method replacements in jar:file:/C:/Users/sxlga/.gradle/caches/modules-2/files-2.1/farseek/Farseek/1.7.10/615e8b0a93f083a50ac1f6d703d4ddf8bc269446/Farseek-1.7.10-2.0.1.jar!/META-INF/farseek_cm.cfg:
  (ReplacedMethod(cpw/mods/fml/common/registry/GameRegistry,registerWorldGenerator,(Lcpw/mods/fml/common/IWorldGenerator;I)V),MethodReplacement(farseek/world/gen/package,registerWorldGenerator))
  (ReplacedMethod(cpw/mods/fml/common/registry/GameRegistry,generateWorld,(IILnet/minecraft/world/World;Lnet/minecraft/world/chunk/IChunkProvider;Lnet/minecraft/world/chunk/IChunkProvider;)V),MethodReplacement(farseek/world/gen/package,generateWorld))
  (ReplacedMethod(cpw/mods/fml/common/WorldAccessContainer,readData,(Lnet/minecraft/world/storage/SaveHandler;Lnet/minecraft/world/storage/WorldInfo;Ljava/util/Map;Lnet/minecraft/nbt/NBTTagCompound;)V),MethodReplacement(farseek/world/storage/package,readData))
[15:03:29] [main/DEBUG] [farseek.farseek/]: Found method replacements in jar:file:/C:/Users/sxlga/.gradle/caches/modules-2/files-2.1/streams/Streams/1.7.10/9ead1486d85c1bf120ddd7fc284ff2091b3d9f61/Streams-1.7.10-0.3.4.jar!/META-INF/farseek_cm.cfg:
  (ReplacedMethod(net/minecraft/block/BlockLiquid,getFlowDirection,(Lnet/minecraft/world/IBlockAccess;IIILnet/minecraft/block/material/Material;)D),MethodReplacement(streams/block/package,getFlowDirection))
  (ReplacedMethod(net/minecraft/world/World,handleMaterialAcceleration,(Lnet/minecraft/util/AxisAlignedBB;Lnet/minecraft/block/material/Material;Lnet/minecraft/entity/Entity;)Z),MethodReplacement(streams/world/package,handleMaterialAcceleration))
  (ReplacedMethod(net/minecraft/world/WorldProvider,createChunkGenerator,()Lnet/minecraft/world/chunk/IChunkProvider;),MethodReplacement(streams/world/gen/package,createChunkGenerator))
  (ReplacedMethod(com/bioxx/tfc/Core/TFC_Core,isFreshWater,(Lnet/minecraft/block/Block;)Z),MethodReplacement(streams/tfc/package,isFreshWater))
  (ReplacedMethod(com/bioxx/tfc/WorldGen/Generators/WorldGenFissure,generate,(Lnet/minecraft/world/World;Ljava/util/Random;III)V),MethodReplacement(streams/tfc/package,generate))
  (ReplacedMethod(com/bioxx/tfc/WorldGen/TFCChunkProviderGenerate,generateStreams,(Lnet/minecraft/world/World;II[Lnet/minecraft/block/Block;[B)V),MethodReplacement(streams/tfc/package,generateStreams))
  (ReplacedMethod(com/bioxx/tfc/Entities/EntityFallingBlockTFC,canReplace,(Lnet/minecraft/world/World;III)Z),MethodReplacement(streams/tfc/package,canReplace))
[15:03:30] [main/TRACE] [FML/]: Registering transformer gtPlusPlus.preloader.asm.transformers.Preloader_Transformer_Handler
[15:03:30] [main/INFO] [FML/]: [GT++ ASM] Chunk Debugging - Enabled: false
[15:03:30] [main/INFO] [FML/]: [GT++ ASM] Gt Nbt Fix - Enabled: true
[15:03:30] [main/INFO] [FML/]: [GT++ ASM] TiCon Fluid Lighting - Enabled: true
[15:03:30] [main/INFO] [FML/]: [GT++ ASM] Gt Tooltip Fix - Enabled: true
[15:03:30] [main/INFO] [FML/]: [GT++ ASM] COFH Patch - Enabled: false
[15:03:30] [main/INFO] [FML/]: [GT++ ASM] Gc Fuel Changes Patch - Enabled: false
[15:03:30] [main/INFO] [FML/]: [GT++ ASM] Railcraft Fluid Flow Patch - Enabled: true
[15:03:30] [main/INFO] [FML/]: [GT++ ASM] Thaumcraft Aspect Safety Patch - Enabled: true
[15:03:30] [main/INFO] [FML/]: [GT++ ASM] Fix bad usage of EntityLivingBase.setHealth Patch - Enabled: false
[15:03:30] [main/INFO] [STDOUT/]: [gtPlusPlus.preloader.asm.transformers.Preloader_Transformer_Handler:<clinit>:30]: [GT++ ASM] Asm Config Location: C:\Users\sxlga\IdeaProjects\Forge_1.7.10_Template_Schrecktech_Reborn\.minecraft\config\GTplusplus\asm.cfg
[15:03:30] [main/INFO] [GT++/]: [DevHelper] mInitMap size: 4819
[15:03:30] [main/INFO] [GT++/]: [DevHelper] mObInitMap size: 1832
[15:03:30] [main/INFO] [GT++/]: [DevHelper] srgToForge size: 4819
[15:03:30] [main/INFO] [GT++/]: [DevHelper] forgeToSrg size: 4311
[15:03:30] [main/INFO] [GT++/]: [DevHelper] obToDeOb size: 1832
[15:03:30] [main/INFO] [GT++/]: [DevHelper] deObToOb size: 1832
[15:03:30] [main/INFO] [STDOUT/]: [gtPlusPlus.preloader.asm.transformers.Preloader_Transformer_Handler:<clinit>:31]: [GT++ ASM] Is DevHelper Valid? true
[15:03:30] [main/DEBUG] [FML/]: Injection complete
[15:03:30] [main/DEBUG] [FML/]: Running coremod plugin for Preloader_FMLLoadingPlugin {gtPlusPlus.preloader.asm.Preloader_FMLLoadingPlugin}
[15:03:30] [main/DEBUG] [FML/]: Running coremod plugin Preloader_FMLLoadingPlugin
[15:03:30] [main/DEBUG] [FML/]: Coremod plugin class Preloader_FMLLoadingPlugin run successfully
[15:03:30] [main/INFO] [LaunchWrapper/]: Loading tweak class name cpw.mods.fml.common.launcher.TerminalTweaker
[15:03:30] [main/INFO] [LaunchWrapper/]: Calling tweak class cpw.mods.fml.common.launcher.TerminalTweaker
[15:03:30] [main/INFO] [LaunchWrapper/]: Launching wrapped minecraft {net.minecraft.client.main.Main}
[15:03:30] [main/INFO] [net.blay09.mods.craftingtweaks.coremod.GuiScreenClassTransformer/]: CraftingTweaks will now patch handleMouseInput in net.minecraft.client.gui.GuiScreen...
[15:03:30] [main/INFO] [net.blay09.mods.craftingtweaks.coremod.GuiScreenClassTransformer/]: CraftingTweaks successfully patched handleMouseInput in net.minecraft.client.gui.GuiScreen!
[15:03:30] [main/INFO] [malisiscore/]: Found hooks for net.minecraft.world.World (net.minecraft.world.World)
[15:03:30] [main/INFO] [HardcoreDarkness/]: Found World Class: net/minecraft/world/World
[15:03:30] [main/INFO] [HardcoreDarkness/]:  - Patched minimal sky light (1)
[15:03:30] [main/INFO] [HardcoreDarkness/]:  - Patched minimal sky light (2)
[15:03:30] [main/INFO] [WarpDriveCore/]: Successful injection in net/minecraft/client/multiplayer/WorldClient
[15:03:30] [main/DEBUG] [OpenMods/]: openmods.core.OpenModsClassTransformer$7$1.createVisitor(OpenModsClassTransformer.java:194): Trying to patch EntityPlayer (class: net.minecraft.entity.player.EntityPlayer)
[15:03:30] [main/TRACE] [OpenMods/]: openmods.utils.StateTracker$StateUpdater.update(StateTracker.java:26): State of player_damage_hook updated from ENABLED to ACTIVATED
[15:03:30] [main/TRACE] [OpenMods/]: openmods.utils.StateTracker$StateUpdater.update(StateTracker.java:26): State of player_damage_hook updated from ACTIVATED to FINISHED
[15:03:30] [main/DEBUG] [OpenMods/]: openblocks.asm.OpenBlocksClassTransformer$1.createVisitor(OpenBlocksClassTransformer.java:19): Trying to patch EntityPlayer.isInBed (class: net.minecraft.entity.player.EntityPlayer)
[15:03:30] [main/DEBUG] [OpenMods/]: openblocks.asm.EntityPlayerVisitor$HookMethodVisitor.visitCode(EntityPlayerVisitor.java:30): isInBed patch applied. Enabling sleeping bags
[15:03:31] [main/INFO] [WarpDriveCore/]: Successful injection in net/minecraft/entity/EntityLivingBase
[15:03:31] [main/DEBUG] [OpenMods/]: openmods.core.OpenModsClassTransformer$2$1.createVisitor(OpenModsClassTransformer.java:104): Trying to apply movement callback (class: net.minecraft.client.entity.EntityPlayerSP)
[15:03:31] [main/TRACE] [OpenMods/]: openmods.utils.StateTracker$StateUpdater.update(StateTracker.java:26): State of movement_callback updated from ENABLED to ACTIVATED
[15:03:31] [main/DEBUG] [OpenMods/]: openmods.movement.MovementPatcher$CallInjector.visitMethodInsn(MovementPatcher.java:67): Callback inserted. Using new movement handler.
[15:03:31] [main/TRACE] [OpenMods/]: openmods.utils.StateTracker$StateUpdater.update(StateTracker.java:26): State of movement_callback updated from ACTIVATED to FINISHED
[15:03:31] [main/DEBUG] [CCL ASM/]: Inserted super call into [net/minecraft/client/renderer/InventoryEffectRenderer.updateScreen()V]
[15:03:31] [main/DEBUG] [CCL ASM/]: Writing method [net/minecraft/client/gui/inventory/GuiContainer.setWorldAndResolution(Lnet/minecraft/client/Minecraft;II)V]
[15:03:31] [main/DEBUG] [CCL ASM/]: Writing method [net/minecraft/client/gui/inventory/GuiContainer.handleKeyboardInput()V]
[15:03:31] [main/DEBUG] [CCL ASM/]: Writing method [net/minecraft/client/gui/inventory/GuiContainer.handleKeyboardInput()V]
[15:03:31] [main/DEBUG] [CCL ASM/]: Writing method [net/minecraft/client/gui/inventory/GuiContainer.handleKeyboardInput()V]
[15:03:31] [main/DEBUG] [CCL ASM/]: Writing method [net/minecraft/client/gui/inventory/GuiContainer.handleMouseInput()V]
[15:03:31] [main/DEBUG] [CCL ASM/]: Writing method [net/minecraft/client/gui/inventory/GuiContainer.public_func_73869_a(CI)V]
[15:03:31] [main/DEBUG] [CCL ASM/]: Writing method [net/minecraft/client/gui/inventory/GuiContainer.public_func_146984_a(Lnet/minecraft/inventory/Slot;III)V]
[15:03:31] [main/DEBUG] [CCL ASM/]: Injecting before method [net/minecraft/client/gui/inventory/GuiContainer.drawScreen(IIF)V]
[15:03:31] [main/ERROR] [LaunchWrapper/]: Unable to launch
java.lang.reflect.InvocationTargetException
	at sun.reflect.NativeMethodAccessorImpl.invoke0(Native Method) ~[?:1.8.0_241]
	at sun.reflect.NativeMethodAccessorImpl.invoke(NativeMethodAccessorImpl.java:62) ~[?:1.8.0_241]
	at sun.reflect.DelegatingMethodAccessorImpl.invoke(DelegatingMethodAccessorImpl.java:43) ~[?:1.8.0_241]
	at java.lang.reflect.Method.invoke(Method.java:498) ~[?:1.8.0_241]
	at net.minecraft.launchwrapper.Launch.launch(Launch.java:135) [launchwrapper-1.12.jar:?]
	at net.minecraft.launchwrapper.Launch.main(Launch.java:28) [launchwrapper-1.12.jar:?]
	at net.minecraftforge.gradle.GradleStartCommon.launch(Unknown Source) [start/:?]
	at GradleStart.main(Unknown Source) [start/:?]
Caused by: java.lang.NoClassDefFoundError: net/minecraft/client/gui/inventory/GuiInventory
	at net.minecraft.client.main.Main.main(Main.java:79) ~[Main.class:?]
	... 8 more
Caused by: java.lang.ClassNotFoundException: net.minecraft.client.gui.inventory.GuiInventory
	at net.minecraft.launchwrapper.LaunchClassLoader.findClass(LaunchClassLoader.java:191) ~[launchwrapper-1.12.jar:?]
	at java.lang.ClassLoader.loadClass(ClassLoader.java:418) ~[?:1.8.0_241]
	at java.lang.ClassLoader.loadClass(ClassLoader.java:351) ~[?:1.8.0_241]
	at net.minecraft.client.main.Main.main(Main.java:79) ~[Main.class:?]
	... 8 more
Caused by: java.lang.NoClassDefFoundError: net/minecraft/client/renderer/InventoryEffectRenderer
	at java.lang.ClassLoader.defineClass1(Native Method) ~[?:1.8.0_241]
	at java.lang.ClassLoader.defineClass(ClassLoader.java:756) ~[?:1.8.0_241]
	at java.security.SecureClassLoader.defineClass(SecureClassLoader.java:142) ~[?:1.8.0_241]
	at net.minecraft.launchwrapper.LaunchClassLoader.findClass(LaunchClassLoader.java:182) ~[launchwrapper-1.12.jar:?]
	at java.lang.ClassLoader.loadClass(ClassLoader.java:418) ~[?:1.8.0_241]
	at java.lang.ClassLoader.loadClass(ClassLoader.java:351) ~[?:1.8.0_241]
	at net.minecraft.client.main.Main.main(Main.java:79) ~[Main.class:?]
	... 8 more
Caused by: java.lang.ClassNotFoundException: net.minecraft.client.renderer.InventoryEffectRenderer
	at net.minecraft.launchwrapper.LaunchClassLoader.findClass(LaunchClassLoader.java:191) ~[launchwrapper-1.12.jar:?]
	at java.lang.ClassLoader.loadClass(ClassLoader.java:418) ~[?:1.8.0_241]
	at java.lang.ClassLoader.loadClass(ClassLoader.java:351) ~[?:1.8.0_241]
	at java.lang.ClassLoader.defineClass1(Native Method) ~[?:1.8.0_241]
	at java.lang.ClassLoader.defineClass(ClassLoader.java:756) ~[?:1.8.0_241]
	at java.security.SecureClassLoader.defineClass(SecureClassLoader.java:142) ~[?:1.8.0_241]
	at net.minecraft.launchwrapper.LaunchClassLoader.findClass(LaunchClassLoader.java:182) ~[launchwrapper-1.12.jar:?]
	at java.lang.ClassLoader.loadClass(ClassLoader.java:418) ~[?:1.8.0_241]
	at java.lang.ClassLoader.loadClass(ClassLoader.java:351) ~[?:1.8.0_241]
	at net.minecraft.client.main.Main.main(Main.java:79) ~[Main.class:?]
	... 8 more
Caused by: java.lang.NoClassDefFoundError: net/minecraft/client/gui/inventory/GuiContainer
	at java.lang.ClassLoader.defineClass1(Native Method) ~[?:1.8.0_241]
	at java.lang.ClassLoader.defineClass(ClassLoader.java:756) ~[?:1.8.0_241]
	at java.security.SecureClassLoader.defineClass(SecureClassLoader.java:142) ~[?:1.8.0_241]
	at net.minecraft.launchwrapper.LaunchClassLoader.findClass(LaunchClassLoader.java:182) ~[launchwrapper-1.12.jar:?]
	at java.lang.ClassLoader.loadClass(ClassLoader.java:418) ~[?:1.8.0_241]
	at java.lang.ClassLoader.loadClass(ClassLoader.java:351) ~[?:1.8.0_241]
	at java.lang.ClassLoader.defineClass1(Native Method) ~[?:1.8.0_241]
	at java.lang.ClassLoader.defineClass(ClassLoader.java:756) ~[?:1.8.0_241]
	at java.security.SecureClassLoader.defineClass(SecureClassLoader.java:142) ~[?:1.8.0_241]
	at net.minecraft.launchwrapper.LaunchClassLoader.findClass(LaunchClassLoader.java:182) ~[launchwrapper-1.12.jar:?]
	at java.lang.ClassLoader.loadClass(ClassLoader.java:418) ~[?:1.8.0_241]
	at java.lang.ClassLoader.loadClass(ClassLoader.java:351) ~[?:1.8.0_241]
	at net.minecraft.client.main.Main.main(Main.java:79) ~[Main.class:?]
	... 8 more
Caused by: java.lang.ClassNotFoundException: net.minecraft.client.gui.inventory.GuiContainer
	at net.minecraft.launchwrapper.LaunchClassLoader.findClass(LaunchClassLoader.java:191) ~[launchwrapper-1.12.jar:?]
	at java.lang.ClassLoader.loadClass(ClassLoader.java:418) ~[?:1.8.0_241]
	at java.lang.ClassLoader.loadClass(ClassLoader.java:351) ~[?:1.8.0_241]
	at java.lang.ClassLoader.defineClass1(Native Method) ~[?:1.8.0_241]
	at java.lang.ClassLoader.defineClass(ClassLoader.java:756) ~[?:1.8.0_241]
	at java.security.SecureClassLoader.defineClass(SecureClassLoader.java:142) ~[?:1.8.0_241]
	at net.minecraft.launchwrapper.LaunchClassLoader.findClass(LaunchClassLoader.java:182) ~[launchwrapper-1.12.jar:?]
	at java.lang.ClassLoader.loadClass(ClassLoader.java:418) ~[?:1.8.0_241]
	at java.lang.ClassLoader.loadClass(ClassLoader.java:351) ~[?:1.8.0_241]
	at java.lang.ClassLoader.defineClass1(Native Method) ~[?:1.8.0_241]
	at java.lang.ClassLoader.defineClass(ClassLoader.java:756) ~[?:1.8.0_241]
	at java.security.SecureClassLoader.defineClass(SecureClassLoader.java:142) ~[?:1.8.0_241]
	at net.minecraft.launchwrapper.LaunchClassLoader.findClass(LaunchClassLoader.java:182) ~[launchwrapper-1.12.jar:?]
	at java.lang.ClassLoader.loadClass(ClassLoader.java:418) ~[?:1.8.0_241]
	at java.lang.ClassLoader.loadClass(ClassLoader.java:351) ~[?:1.8.0_241]
	at net.minecraft.client.main.Main.main(Main.java:79) ~[Main.class:?]
	... 8 more
Caused by: java.lang.RuntimeException: java.lang.RuntimeException: Error transforming method: [net/minecraft/client/gui/inventory/GuiContainer.drawScreen(IIF)V]
	at codechicken.nei.asm.NEITransformer.transform(NEITransformer.java:267) ~[NotEnoughItems-1.7.10-2.0.1-GTNH-universal-2906319.jar:?]
	at net.minecraft.launchwrapper.LaunchClassLoader.runTransformers(LaunchClassLoader.java:279) ~[launchwrapper-1.12.jar:?]
	at net.minecraft.launchwrapper.LaunchClassLoader.findClass(LaunchClassLoader.java:176) ~[launchwrapper-1.12.jar:?]
	at java.lang.ClassLoader.loadClass(ClassLoader.java:418) ~[?:1.8.0_241]
	at java.lang.ClassLoader.loadClass(ClassLoader.java:351) ~[?:1.8.0_241]
	at java.lang.ClassLoader.defineClass1(Native Method) ~[?:1.8.0_241]
	at java.lang.ClassLoader.defineClass(ClassLoader.java:756) ~[?:1.8.0_241]
	at java.security.SecureClassLoader.defineClass(SecureClassLoader.java:142) ~[?:1.8.0_241]
	at net.minecraft.launchwrapper.LaunchClassLoader.findClass(LaunchClassLoader.java:182) ~[launchwrapper-1.12.jar:?]
	at java.lang.ClassLoader.loadClass(ClassLoader.java:418) ~[?:1.8.0_241]
	at java.lang.ClassLoader.loadClass(ClassLoader.java:351) ~[?:1.8.0_241]
	at java.lang.ClassLoader.defineClass1(Native Method) ~[?:1.8.0_241]
	at java.lang.ClassLoader.defineClass(ClassLoader.java:756) ~[?:1.8.0_241]
	at java.security.SecureClassLoader.defineClass(SecureClassLoader.java:142) ~[?:1.8.0_241]
	at net.minecraft.launchwrapper.LaunchClassLoader.findClass(LaunchClassLoader.java:182) ~[launchwrapper-1.12.jar:?]
	at java.lang.ClassLoader.loadClass(ClassLoader.java:418) ~[?:1.8.0_241]
	at java.lang.ClassLoader.loadClass(ClassLoader.java:351) ~[?:1.8.0_241]
	at net.minecraft.client.main.Main.main(Main.java:79) ~[Main.class:?]
	... 8 more
Caused by: java.lang.RuntimeException: Error transforming method: [net/minecraft/client/gui/inventory/GuiContainer.drawScreen(IIF)V]
	at codechicken.lib.asm.ModularASMTransformer$MethodTransformer.transform(ModularASMTransformer.java:90) ~[CodeChickenLib-1.7.10-1.1.3.140-dev.jar:?]
	at codechicken.lib.asm.ModularASMTransformer$ClassNodeTransformerList.transform(ModularASMTransformer.java:36) ~[CodeChickenLib-1.7.10-1.1.3.140-dev.jar:?]
	at codechicken.lib.asm.ModularASMTransformer.transform(ModularASMTransformer.java:283) ~[CodeChickenLib-1.7.10-1.1.3.140-dev.jar:?]
	at codechicken.nei.asm.NEITransformer.transform(NEITransformer.java:265) ~[NotEnoughItems-1.7.10-2.0.1-GTNH-universal-2906319.jar:?]
	at net.minecraft.launchwrapper.LaunchClassLoader.runTransformers(LaunchClassLoader.java:279) ~[launchwrapper-1.12.jar:?]
	at net.minecraft.launchwrapper.LaunchClassLoader.findClass(LaunchClassLoader.java:176) ~[launchwrapper-1.12.jar:?]
	at java.lang.ClassLoader.loadClass(ClassLoader.java:418) ~[?:1.8.0_241]
	at java.lang.ClassLoader.loadClass(ClassLoader.java:351) ~[?:1.8.0_241]
	at java.lang.ClassLoader.defineClass1(Native Method) ~[?:1.8.0_241]
	at java.lang.ClassLoader.defineClass(ClassLoader.java:756) ~[?:1.8.0_241]
	at java.security.SecureClassLoader.defineClass(SecureClassLoader.java:142) ~[?:1.8.0_241]
	at net.minecraft.launchwrapper.LaunchClassLoader.findClass(LaunchClassLoader.java:182) ~[launchwrapper-1.12.jar:?]
	at java.lang.ClassLoader.loadClass(ClassLoader.java:418) ~[?:1.8.0_241]
	at java.lang.ClassLoader.loadClass(ClassLoader.java:351) ~[?:1.8.0_241]
	at java.lang.ClassLoader.defineClass1(Native Method) ~[?:1.8.0_241]
	at java.lang.ClassLoader.defineClass(ClassLoader.java:756) ~[?:1.8.0_241]
	at java.security.SecureClassLoader.defineClass(SecureClassLoader.java:142) ~[?:1.8.0_241]
	at net.minecraft.launchwrapper.LaunchClassLoader.findClass(LaunchClassLoader.java:182) ~[launchwrapper-1.12.jar:?]
	at java.lang.ClassLoader.loadClass(ClassLoader.java:418) ~[?:1.8.0_241]
	at java.lang.ClassLoader.loadClass(ClassLoader.java:351) ~[?:1.8.0_241]
	at net.minecraft.client.main.Main.main(Main.java:79) ~[Main.class:?]
	... 8 more
Caused by: java.lang.RuntimeException: Needle not found in Haystack:
    ALOAD 0
    GETFIELD net/minecraft/client/gui/inventory/GuiContainer.manager : Lcodechicken/nei/guihook/GuiContainerManager;
    INVOKEVIRTUAL codechicken/nei/guihook/GuiContainerManager.preDraw ()V
   L0
    LINENUMBER 92 L0
    ALOAD 0
    INVOKEVIRTUAL net/minecraft/client/gui/inventory/GuiContainer.drawDefaultBackground ()V
   L1
    LINENUMBER 93 L1
    ALOAD 0
    GETFIELD net/minecraft/client/gui/inventory/GuiContainer.guiLeft : I
    ISTORE 4
   L2
    LINENUMBER 94 L2
    ALOAD 0
    GETFIELD net/minecraft/client/gui/inventory/GuiContainer.guiTop : I
    ISTORE 5
   L3
    LINENUMBER 95 L3
    ALOAD 0
    FLOAD 3
    ILOAD 1
    ILOAD 2
    INVOKEVIRTUAL net/minecraft/client/gui/inventory/GuiContainer.drawGuiContainerBackgroundLayer (FII)V
   L4
    LINENUMBER 96 L4
    LDC 32826
    INVOKESTATIC org/lwjgl/opengl/GL11.glDisable (I)V
   L5
    LINENUMBER 97 L5
    INVOKESTATIC net/minecraft/client/renderer/RenderHelper.disableStandardItemLighting ()V
   L6
    LINENUMBER 98 L6
    SIPUSH 2896
    INVOKESTATIC org/lwjgl/opengl/GL11.glDisable (I)V
   L7
    LINENUMBER 99 L7
    SIPUSH 2929
    INVOKESTATIC org/lwjgl/opengl/GL11.glDisable (I)V
   L8
    LINENUMBER 100 L8
    ALOAD 0
    ILOAD 1
    ILOAD 2
    FLOAD 3
    INVOKESPECIAL net/minecraft/client/gui/GuiScreen.drawScreen (IIF)V
   L9
    LINENUMBER 101 L9
    INVOKESTATIC net/minecraft/client/renderer/RenderHelper.enableGUIStandardItemLighting ()V
   L10
    LINENUMBER 102 L10
    INVOKESTATIC org/lwjgl/opengl/GL11.glPushMatrix ()V
   L11
    LINENUMBER 103 L11
    ILOAD 4
    I2F
    ILOAD 5
    I2F
    FCONST_0
    INVOKESTATIC org/lwjgl/opengl/GL11.glTranslatef (FFF)V
   L12
    LINENUMBER 104 L12
    FCONST_1
    FCONST_1
    FCONST_1
    FCONST_1
    INVOKESTATIC org/lwjgl/opengl/GL11.glColor4f (FFFF)V
   L13
    LINENUMBER 105 L13
    LDC 32826
    INVOKESTATIC org/lwjgl/opengl/GL11.glEnable (I)V
   L14
    LINENUMBER 106 L14
    ALOAD 0
    ACONST_NULL
    PUTFIELD net/minecraft/client/gui/inventory/GuiContainer.theSlot : Lnet/minecraft/inventory/Slot;
   L15
    LINENUMBER 107 L15
    SIPUSH 240
    ISTORE 6
   L16
    LINENUMBER 108 L16
    SIPUSH 240
    ISTORE 7
   L17
    LINENUMBER 109 L17
    GETSTATIC net/minecraft/client/renderer/OpenGlHelper.lightmapTexUnit : I
    ILOAD 6
    I2F
    FCONST_1
    FDIV
    ILOAD 7
    I2F
    FCONST_1
    FDIV
    INVOKESTATIC net/minecraft/client/renderer/OpenGlHelper.setLightmapTextureCoords (IFF)V
   L18
    LINENUMBER 110 L18
    FCONST_1
    FCONST_1
    FCONST_1
    FCONST_1
    INVOKESTATIC org/lwjgl/opengl/GL11.glColor4f (FFFF)V
   L19
    LINENUMBER 113 L19
    ICONST_0
    ISTORE 8
   L20
   FRAME FULL [net/minecraft/client/gui/inventory/GuiContainer I I F I I I I I] []
    ILOAD 8
    ALOAD 0
    GETFIELD net/minecraft/client/gui/inventory/GuiContainer.inventorySlots : Lnet/minecraft/inventory/Container;
    GETFIELD net/minecraft/inventory/Container.inventorySlots : Ljava/util/List;
    INVOKEINTERFACE java/util/List.size ()I
    IF_ICMPGE L21
   L22
    LINENUMBER 115 L22
    ALOAD 0
    GETFIELD net/minecraft/client/gui/inventory/GuiContainer.inventorySlots : Lnet/minecraft/inventory/Container;
    GETFIELD net/minecraft/inventory/Container.inventorySlots : Ljava/util/List;
    ILOAD 8
    INVOKEINTERFACE java/util/List.get (I)Ljava/lang/Object;
    CHECKCAST net/minecraft/inventory/Slot
    ASTORE 9
   L23
    LINENUMBER 116 L23
    ALOAD 0
    ALOAD 9
    INVOKESPECIAL net/minecraft/client/gui/inventory/GuiContainer.drawSlot (Lnet/minecraft/inventory/Slot;)V
   L24
    LINENUMBER 118 L24
    ALOAD 0
    ALOAD 9
    ILOAD 1
    ILOAD 2
    INVOKESPECIAL net/minecraft/client/gui/inventory/GuiContainer.isMouseOverSlot (Lnet/minecraft/inventory/Slot;II)Z
    IFEQ L25
    ALOAD 9
    INVOKEVIRTUAL net/minecraft/inventory/Slot.canBeHovered ()Z
    IFEQ L25
   L26
    LINENUMBER 120 L26
    ALOAD 0
    ALOAD 9
    PUTFIELD net/minecraft/client/gui/inventory/GuiContainer.theSlot : Lnet/minecraft/inventory/Slot;
   L27
    LINENUMBER 121 L27
    SIPUSH 2896
    INVOKESTATIC org/lwjgl/opengl/GL11.glDisable (I)V
   L28
    LINENUMBER 122 L28
    SIPUSH 2929
    INVOKESTATIC org/lwjgl/opengl/GL11.glDisable (I)V
   L29
    LINENUMBER 123 L29
    ALOAD 9
    GETFIELD net/minecraft/inventory/Slot.xDisplayPosition : I
    ISTORE 10
   L30
    LINENUMBER 124 L30
    ALOAD 9
    GETFIELD net/minecraft/inventory/Slot.yDisplayPosition : I
    ISTORE 11
   L31
    LINENUMBER 125 L31
    ICONST_1
    ICONST_1
    ICONST_1
    ICONST_0
    INVOKESTATIC org/lwjgl/opengl/GL11.glColorMask (ZZZZ)V
   L32
    LINENUMBER 126 L32
    ALOAD 0
    ILOAD 10
    ILOAD 11
    ILOAD 10
    BIPUSH 16
    IADD
    ILOAD 11
    BIPUSH 16
    IADD
    LDC -2130706433
    LDC -2130706433
    INVOKEVIRTUAL net/minecraft/client/gui/inventory/GuiContainer.drawGradientRect (IIIIII)V
   L33
    LINENUMBER 127 L33
    ICONST_1
    ICONST_1
    ICONST_1
    ICONST_1
    INVOKESTATIC org/lwjgl/opengl/GL11.glColorMask (ZZZZ)V
   L34
    LINENUMBER 128 L34
    SIPUSH 2896
    INVOKESTATIC org/lwjgl/opengl/GL11.glEnable (I)V
   L35
    LINENUMBER 129 L35
    SIPUSH 2929
    INVOKESTATIC org/lwjgl/opengl/GL11.glEnable (I)V
   L25
    LINENUMBER 113 L25
   FRAME FULL [net/minecraft/client/gui/inventory/GuiContainer I I F I I I I I] []
    IINC 8 1
    GOTO L20
   L21
    LINENUMBER 135 L21
   FRAME FULL [net/minecraft/client/gui/inventory/GuiContainer I I F I I I I] []
    SIPUSH 2896
    INVOKESTATIC org/lwjgl/opengl/GL11.glDisable (I)V
   L36
    LINENUMBER 136 L36
    ALOAD 0
    ILOAD 1
    ILOAD 2
    INVOKEVIRTUAL net/minecraft/client/gui/inventory/GuiContainer.drawGuiContainerForegroundLayer (II)V
   L37
    LINENUMBER 137 L37
    SIPUSH 2896
    INVOKESTATIC org/lwjgl/opengl/GL11.glEnable (I)V
   L38
    LINENUMBER 138 L38
    ALOAD 0
    GETFIELD net/minecraft/client/gui/inventory/GuiContainer.mc : Lnet/minecraft/client/Minecraft;
    GETFIELD net/minecraft/client/Minecraft.thePlayer : Lnet/minecraft/client/entity/EntityClientPlayerMP;
    GETFIELD net/minecraft/client/entity/EntityClientPlayerMP.inventory : Lnet/minecraft/entity/player/InventoryPlayer;
    ASTORE 8
   L39
    LINENUMBER 139 L39
    ALOAD 0
    GETFIELD net/minecraft/client/gui/inventory/GuiContainer.draggedStack : Lnet/minecraft/item/ItemStack;
    IFNONNULL L40
    ALOAD 8
    INVOKEVIRTUAL net/minecraft/entity/player/InventoryPlayer.getItemStack ()Lnet/minecraft/item/ItemStack;
    GOTO L41
   L40
   FRAME FULL [net/minecraft/client/gui/inventory/GuiContainer I I F I I I I net/minecraft/entity/player/InventoryPlayer] []
    ALOAD 0
    GETFIELD net/minecraft/client/gui/inventory/GuiContainer.draggedStack : Lnet/minecraft/item/ItemStack;
   L41
   FRAME FULL [net/minecraft/client/gui/inventory/GuiContainer I I F I I I I net/minecraft/entity/player/InventoryPlayer] [net/minecraft/item/ItemStack]
    ASTORE 9
   L42
    LINENUMBER 141 L42
    ALOAD 9
    IFNULL L43
   L44
    LINENUMBER 143 L44
    BIPUSH 8
    ISTORE 10
   L45
    LINENUMBER 144 L45
    ALOAD 0
    GETFIELD net/minecraft/client/gui/inventory/GuiContainer.draggedStack : Lnet/minecraft/item/ItemStack;
    IFNONNULL L46
    BIPUSH 8
    GOTO L47
   L46
   FRAME FULL [net/minecraft/client/gui/inventory/GuiContainer I I F I I I I net/minecraft/entity/player/InventoryPlayer net/minecraft/item/ItemStack I] []
    BIPUSH 16
   L47
   FRAME FULL [net/minecraft/client/gui/inventory/GuiContainer I I F I I I I net/minecraft/entity/player/InventoryPlayer net/minecraft/item/ItemStack I] [I]
    ISTORE 11
   L48
    LINENUMBER 145 L48
    ACONST_NULL
    ASTORE 12
   L49
    LINENUMBER 147 L49
    ALOAD 0
    GETFIELD net/minecraft/client/gui/inventory/GuiContainer.draggedStack : Lnet/minecraft/item/ItemStack;
    IFNULL L50
    ALOAD 0
    GETFIELD net/minecraft/client/gui/inventory/GuiContainer.isRightMouseClick : Z
    IFEQ L50
   L51
    LINENUMBER 149 L51
    ALOAD 9
    INVOKEVIRTUAL net/minecraft/item/ItemStack.copy ()Lnet/minecraft/item/ItemStack;
    ASTORE 9
   L52
    LINENUMBER 150 L52
    ALOAD 9
    ALOAD 9
    GETFIELD net/minecraft/item/ItemStack.stackSize : I
    I2F
    FCONST_2
    FDIV
    INVOKESTATIC net/minecraft/util/MathHelper.ceiling_float_int (F)I
    PUTFIELD net/minecraft/item/ItemStack.stackSize : I
    GOTO L53
   L50
    LINENUMBER 152 L50
   FRAME FULL [net/minecraft/client/gui/inventory/GuiContainer I I F I I I I net/minecraft/entity/player/InventoryPlayer net/minecraft/item/ItemStack I I java/lang/String] []
    ALOAD 0
    GETFIELD net/minecraft/client/gui/inventory/GuiContainer.dragSplitting : Z
    IFEQ L53
    ALOAD 0
    GETFIELD net/minecraft/client/gui/inventory/GuiContainer.dragSplittingSlots : Ljava/util/Set;
    INVOKEINTERFACE java/util/Set.size ()I
    ICONST_1
    IF_ICMPLE L53
   L54
    LINENUMBER 154 L54
    ALOAD 9
    INVOKEVIRTUAL net/minecraft/item/ItemStack.copy ()Lnet/minecraft/item/ItemStack;
    ASTORE 9
   L55
    LINENUMBER 155 L55
    ALOAD 9
    ALOAD 0
    GETFIELD net/minecraft/client/gui/inventory/GuiContainer.dragSplittingRemnant : I
    PUTFIELD net/minecraft/item/ItemStack.stackSize : I
   L56
    LINENUMBER 157 L56
    ALOAD 9
    GETFIELD net/minecraft/item/ItemStack.stackSize : I
    IFNE L53
   L57
    LINENUMBER 159 L57
    NEW java/lang/StringBuilder
    DUP
    INVOKESPECIAL java/lang/StringBuilder.<init> ()V
    LDC ""
    INVOKEVIRTUAL java/lang/StringBuilder.append (Ljava/lang/String;)Ljava/lang/StringBuilder;
    GETSTATIC net/minecraft/util/EnumChatFormatting.YELLOW : Lnet/minecraft/util/EnumChatFormatting;
    INVOKEVIRTUAL java/lang/StringBuilder.append (Ljava/lang/Object;)Ljava/lang/StringBuilder;
    LDC "0"
    INVOKEVIRTUAL java/lang/StringBuilder.append (Ljava/lang/String;)Ljava/lang/StringBuilder;
    INVOKEVIRTUAL java/lang/StringBuilder.toString ()Ljava/lang/String;
    ASTORE 12
   L53
    LINENUMBER 163 L53
   FRAME FULL [net/minecraft/client/gui/inventory/GuiContainer I I F I I I I net/minecraft/entity/player/InventoryPlayer net/minecraft/item/ItemStack I I java/lang/String] []
    ALOAD 0
    ALOAD 9
    ILOAD 1
    ILOAD 4
    ISUB
    ILOAD 10
    ISUB
    ILOAD 2
    ILOAD 5
    ISUB
    ILOAD 11
    ISUB
    ALOAD 12
    INVOKESPECIAL net/minecraft/client/gui/inventory/GuiContainer.drawItemStack (Lnet/minecraft/item/ItemStack;IILjava/lang/String;)V
   L43
    LINENUMBER 166 L43
   FRAME FULL [net/minecraft/client/gui/inventory/GuiContainer I I F I I I I net/minecraft/entity/player/InventoryPlayer net/minecraft/item/ItemStack] []
    ALOAD 0
    GETFIELD net/minecraft/client/gui/inventory/GuiContainer.returningStack : Lnet/minecraft/item/ItemStack;
    IFNULL L58
   L59
    LINENUMBER 168 L59
    INVOKESTATIC net/minecraft/client/Minecraft.getSystemTime ()J
    ALOAD 0
    GETFIELD net/minecraft/client/gui/inventory/GuiContainer.returningStackTime : J
    LSUB
    L2F
    LDC 100.0
    FDIV
    FSTORE 10
   L60
    LINENUMBER 170 L60
    FLOAD 10
    FCONST_1
    FCMPL
    IFLT L61
   L62
    LINENUMBER 172 L62
    FCONST_1
    FSTORE 10
   L63
    LINENUMBER 173 L63
    ALOAD 0
    ACONST_NULL
    PUTFIELD net/minecraft/client/gui/inventory/GuiContainer.returningStack : Lnet/minecraft/item/ItemStack;
   L61
    LINENUMBER 176 L61
   FRAME FULL [net/minecraft/client/gui/inventory/GuiContainer I I F I I I I net/minecraft/entity/player/InventoryPlayer net/minecraft/item/ItemStack F] []
    ALOAD 0
    GETFIELD net/minecraft/client/gui/inventory/GuiContainer.returningStackDestSlot : Lnet/minecraft/inventory/Slot;
    GETFIELD net/minecraft/inventory/Slot.xDisplayPosition : I
    ALOAD 0
    GETFIELD net/minecraft/client/gui/inventory/GuiContainer.touchUpX : I
    ISUB
    ISTORE 11
   L64
    LINENUMBER 177 L64
    ALOAD 0
    GETFIELD net/minecraft/client/gui/inventory/GuiContainer.returningStackDestSlot : Lnet/minecraft/inventory/Slot;
    GETFIELD net/minecraft/inventory/Slot.yDisplayPosition : I
    ALOAD 0
    GETFIELD net/minecraft/client/gui/inventory/GuiContainer.touchUpY : I
    ISUB
    ISTORE 12
   L65
    LINENUMBER 178 L65
    ALOAD 0
    GETFIELD net/minecraft/client/gui/inventory/GuiContainer.touchUpX : I
    ILOAD 11
    I2F
    FLOAD 10
    FMUL
    F2I
    IADD
    ISTORE 13
   L66
    LINENUMBER 179 L66
    ALOAD 0
    GETFIELD net/minecraft/client/gui/inventory/GuiContainer.touchUpY : I
    ILOAD 12
    I2F
    FLOAD 10
    FMUL
    F2I
    IADD
    ISTORE 14
   L67
    LINENUMBER 180 L67
    ALOAD 0
    ALOAD 0
    GETFIELD net/minecraft/client/gui/inventory/GuiContainer.returningStack : Lnet/minecraft/item/ItemStack;
    ILOAD 13
    ILOAD 14
    ACONST_NULL
    CHECKCAST java/lang/String
    INVOKESPECIAL net/minecraft/client/gui/inventory/GuiContainer.drawItemStack (Lnet/minecraft/item/ItemStack;IILjava/lang/String;)V
   L58
    LINENUMBER 183 L58
   FRAME FULL [net/minecraft/client/gui/inventory/GuiContainer I I F I I I I net/minecraft/entity/player/InventoryPlayer net/minecraft/item/ItemStack] []
    INVOKESTATIC org/lwjgl/opengl/GL11.glPopMatrix ()V
   L68
    LINENUMBER 185 L68
    ALOAD 8
    INVOKEVIRTUAL net/minecraft/entity/player/InventoryPlayer.getItemStack ()Lnet/minecraft/item/ItemStack;
    IFNONNULL L69
    ALOAD 0
    GETFIELD net/minecraft/client/gui/inventory/GuiContainer.theSlot : Lnet/minecraft/inventory/Slot;
    IFNULL L69
    ALOAD 0
    GETFIELD net/minecraft/client/gui/inventory/GuiContainer.theSlot : Lnet/minecraft/inventory/Slot;
    INVOKEVIRTUAL net/minecraft/inventory/Slot.getHasStack ()Z
    IFEQ L69
   L70
    LINENUMBER 187 L70
    ALOAD 0
    GETFIELD net/minecraft/client/gui/inventory/GuiContainer.theSlot : Lnet/minecraft/inventory/Slot;
    INVOKEVIRTUAL net/minecraft/inventory/Slot.getStack ()Lnet/minecraft/item/ItemStack;
    ASTORE 10
   L71
    LINENUMBER 188 L71
    ALOAD 0
    ALOAD 10
    ILOAD 1
    ILOAD 2
    INVOKEVIRTUAL net/minecraft/client/gui/inventory/GuiContainer.renderToolTip (Lnet/minecraft/item/ItemStack;II)V
   L69
    LINENUMBER 191 L69
   FRAME FULL [net/minecraft/client/gui/inventory/GuiContainer I I F I I I I net/minecraft/entity/player/InventoryPlayer net/minecraft/item/ItemStack] []
    SIPUSH 2896
    INVOKESTATIC org/lwjgl/opengl/GL11.glEnable (I)V
   L72
    LINENUMBER 192 L72
    SIPUSH 2929
    INVOKESTATIC org/lwjgl/opengl/GL11.glEnable (I)V
   L73
    LINENUMBER 193 L73
    INVOKESTATIC net/minecraft/client/renderer/RenderHelper.enableStandardItemLighting ()V
   L74
    LINENUMBER 194 L74
    RETURN
   L75


    INVOKEVIRTUAL net/minecraft/inventory/Slot.func_111238_b ()Z
    IFEQ L0

	at codechicken.lib.asm.InsnComparator.findN(InsnComparator.java:181) ~[CodeChickenLib-1.7.10-1.1.3.140-dev.jar:?]
	at codechicken.lib.asm.InsnComparator.findN(InsnComparator.java:187) ~[CodeChickenLib-1.7.10-1.1.3.140-dev.jar:?]
	at codechicken.lib.asm.ModularASMTransformer$MethodInjector.transform(ModularASMTransformer.java:199) ~[CodeChickenLib-1.7.10-1.1.3.140-dev.jar:?]
	at codechicken.lib.asm.ModularASMTransformer$MethodTransformer.transform(ModularASMTransformer.java:88) ~[CodeChickenLib-1.7.10-1.1.3.140-dev.jar:?]
	at codechicken.lib.asm.ModularASMTransformer$ClassNodeTransformerList.transform(ModularASMTransformer.java:36) ~[CodeChickenLib-1.7.10-1.1.3.140-dev.jar:?]
	at codechicken.lib.asm.ModularASMTransformer.transform(ModularASMTransformer.java:283) ~[CodeChickenLib-1.7.10-1.1.3.140-dev.jar:?]
	at codechicken.nei.asm.NEITransformer.transform(NEITransformer.java:265) ~[NotEnoughItems-1.7.10-2.0.1-GTNH-universal-2906319.jar:?]
	at net.minecraft.launchwrapper.LaunchClassLoader.runTransformers(LaunchClassLoader.java:279) ~[launchwrapper-1.12.jar:?]
	at net.minecraft.launchwrapper.LaunchClassLoader.findClass(LaunchClassLoader.java:176) ~[launchwrapper-1.12.jar:?]
	at java.lang.ClassLoader.loadClass(ClassLoader.java:418) ~[?:1.8.0_241]
	at java.lang.ClassLoader.loadClass(ClassLoader.java:351) ~[?:1.8.0_241]
	at java.lang.ClassLoader.defineClass1(Native Method) ~[?:1.8.0_241]
	at java.lang.ClassLoader.defineClass(ClassLoader.java:756) ~[?:1.8.0_241]
	at java.security.SecureClassLoader.defineClass(SecureClassLoader.java:142) ~[?:1.8.0_241]
	at net.minecraft.launchwrapper.LaunchClassLoader.findClass(LaunchClassLoader.java:182) ~[launchwrapper-1.12.jar:?]
	at java.lang.ClassLoader.loadClass(ClassLoader.java:418) ~[?:1.8.0_241]
	at java.lang.ClassLoader.loadClass(ClassLoader.java:351) ~[?:1.8.0_241]
	at java.lang.ClassLoader.defineClass1(Native Method) ~[?:1.8.0_241]
	at java.lang.ClassLoader.defineClass(ClassLoader.java:756) ~[?:1.8.0_241]
	at java.security.SecureClassLoader.defineClass(SecureClassLoader.java:142) ~[?:1.8.0_241]
	at net.minecraft.launchwrapper.LaunchClassLoader.findClass(LaunchClassLoader.java:182) ~[launchwrapper-1.12.jar:?]
	at java.lang.ClassLoader.loadClass(ClassLoader.java:418) ~[?:1.8.0_241]
	at java.lang.ClassLoader.loadClass(ClassLoader.java:351) ~[?:1.8.0_241]
	at net.minecraft.client.main.Main.main(Main.java:79) ~[Main.class:?]
	... 8 more
[15:03:31] [main/INFO] [STDERR/]: [java.lang.Throwable$WrappedPrintStream:println:749]: cpw.mods.fml.relauncher.FMLSecurityManager$ExitTrappedException
[15:03:31] [main/INFO] [STDERR/]: [java.lang.Throwable$WrappedPrintStream:println:749]: 	at cpw.mods.fml.relauncher.FMLSecurityManager.checkPermission(FMLSecurityManager.java:25)
[15:03:31] [main/INFO] [STDERR/]: [java.lang.Throwable$WrappedPrintStream:println:749]: 	at java.lang.SecurityManager.checkExit(SecurityManager.java:761)
[15:03:31] [main/INFO] [STDERR/]: [java.lang.Throwable$WrappedPrintStream:println:749]: 	at java.lang.Runtime.exit(Runtime.java:107)
[15:03:31] [main/INFO] [STDERR/]: [java.lang.Throwable$WrappedPrintStream:println:749]: 	at java.lang.System.exit(System.java:971)
[15:03:31] [main/INFO] [STDERR/]: [java.lang.Throwable$WrappedPrintStream:println:749]: 	at net.minecraft.launchwrapper.Launch.launch(Launch.java:138)
[15:03:31] [main/INFO] [STDERR/]: [java.lang.Throwable$WrappedPrintStream:println:749]: 	at net.minecraft.launchwrapper.Launch.main(Launch.java:28)
[15:03:31] [main/INFO] [STDERR/]: [java.lang.Throwable$WrappedPrintStream:println:749]: 	at net.minecraftforge.gradle.GradleStartCommon.launch(Unknown Source)
[15:03:31] [main/INFO] [STDERR/]: [java.lang.Throwable$WrappedPrintStream:println:749]: 	at GradleStart.main(Unknown Source)
